Workbook

Sheet Assumptions
A1: mTBI Screening Tool — Financial Model — Assumptions
A2: Single source of truth. Every other tab references this one. Edit only blue (input) or orange (provisional) cells. Set unused tier/role/capex slots to 0 — formulas adapt automatically.
A4: Year | C4: Y1 | D4: Y2 | E4: Y3 | F4: Y4 | G4: Y5 | H4: Y6 | I4: Y7
A5: Period number | C5: 1 | D5: 2 | E5: 3 | F5: 4 | G5: 5 | H5: 6 | I5: 7 | L5: (driver)
A6: Calendar year | C6: 2026 | D6: 2027 | E6: 2028 | F6: 2029 | G6: 2030 | H6: 2031 | I6: 2032
A7: Phase | C7: 1 | D7: 1 | E7: 2 | F7: 2 | G7: 3 | H7: 3 | I7: 3 | L7: (driver) | M7: 1 = research validation, 2 = first commercial, 3 = scale-up
A9: 0. SANITY CHECKS
A10: Total headsets = 3 × inst + parent | C10: =IF(C15=$B$26*C28+C29, "OK", "FAIL") -> OK | D10: =IF(D15=$B$26*D28+D29, "OK", "FAIL") -> OK | E10: =IF(E15=$B$26*E28+E29, "OK", "FAIL") -> OK | F10: =IF(F15=$B$26*F28+F29, "OK", "FAIL") -> OK | G10: =IF(G15=$B$26*G28+G29, "OK", "FAIL") -> OK | H10: =IF(H15=$B$26*H28+H29, "OK", "FAIL") -> OK | I10: =IF(I15=$B$26*I28+I29, "OK", "FAIL") -> OK | M10: Should display OK across the row (row 15 = $B$26·row28 + row29)
A11: Cash never below buffer | B11: =IF(MIN('Cash flow'!C39:I39) >= $B$127, "OK", "BREACH") -> OK | M11: From Cash flow tab — checks all 9 closing-cash years
A12: Balance sheet balances | B12: =IF(SUMPRODUCT(--(ABS('Balance sheet'!C34:K34)<1))=9, "OK", "FAIL") -> OK | M12: From Balance sheet tab — sum of absolute differences
A14: 1. ADOPTION RAMP (derived from GTM channel mix, §3)
A15: Total headsets sold per year (derived) | C15: =$B$26*C28 + C29 -> 0 | D15: =$B$26*D28 + D29 -> 0 | E15: =$B$26*E28 + E29 -> 90 | F15: =$B$26*F28 + F29 -> 270 | G15: =$B$26*G28 + G29 -> 1491 | H15: =$B$26*H28 + H29 -> 3154 | I15: =$B$26*I28 + I29 -> 7575 | L15: headsets | M15: = 3 × institutional buyers + parent buyers (rows 28–29)
A16: Annual subscription churn | B16: 0.1 | L16: % per year | M16: ch.9 §9.4 indicative; applied to start-of-year base
A17: Active headset subscriptions (end of year) | C17: =INDEX($C$28:$K$28, 1, MAX(C5 - Scenarios!$B$26, MIN(C5, 3))) * $B$26 * Scenarios!$B$20 * $B$33 + OFFSET(C17, 0, -1) * (1 - $B$16 * Scenarios!$B$22) -> 0 | D17: =INDEX($C$28:$K$28, 1, MAX(D5 - Scenarios!$B$26, MIN(D5, 3))) * $B$26 * Scenarios!$B$20 * $B$33 + OFFSET(D17, 0, -1) * (1 - $B$16 * Scenarios!$B$22) -> 0 | E17: =INDEX($C$28:$K$28, 1, MAX(E5 - Scenarios!$B$26, MIN(E5, 3))) * $B$26 * Scenarios!$B$20 * $B$33 + OFFSET(E17, 0, -1) * (1 - $B$16 * Scenarios!$B$22) -> 90 | F17: =INDEX($C$28:$K$28, 1, MAX(F5 - Scenarios!$B$26, MIN(F5, 3))) * $B$26 * Scenarios!$B$20 * $B$33 + OFFSET(F17, 0, -1) * (1 - $B$16 * Scenarios!$B$22) -> 351 | G17: =INDEX($C$28:$K$28, 1, MAX(G5 - Scenarios!$B$26, MIN(G5, 3))) * $B$26 * Scenarios!$B$20 * $B$33 + OFFSET(G17, 0, -1) * (1 - $B$16 * Scenarios!$B$22) -> 765.9 | H17: =INDEX($C$28:$K$28, 1, MAX(H5 - Scenarios!$B$26, MIN(H5, 3))) * $B$26 * Scenarios!$B$20 * $B$33 + OFFSET(H17, 0, -1) * (1 - $B$16 * Scenarios!$B$22) -> 1889.31 | I17: =INDEX($C$28:$K$28, 1, MAX(I5 - Scenarios!$B$26, MIN(I5, 3))) * $B$26 * Scenarios!$B$20 * $B$33 + OFFSET(I17, 0, -1) * (1 - $B$16 * Scenarios!$B$22) -> 3950.379 | L17: subs | M17: prior × (1 − churn) + institutional buyers × headsets/inst × attach × adoption
A18: Average headset subscriptions (year) | C18: =(C17 + OFFSET(C17, 0, -1)) / 2 -> 0 | D18: =(D17 + OFFSET(D17, 0, -1)) / 2 -> 0 | E18: =(E17 + OFFSET(E17, 0, -1)) / 2 -> 45 | F18: =(F17 + OFFSET(F17, 0, -1)) / 2 -> 220.5 | G18: =(G17 + OFFSET(G17, 0, -1)) / 2 -> 558.45 | H18: =(H17 + OFFSET(H17, 0, -1)) / 2 -> 1327.605 | I18: =(I17 + OFFSET(I17, 0, -1)) / 2 -> 2919.8445 | L18: subs | M18: (start + end) / 2; drives subscription revenue
A19: Cumulative headsets sold (end of year) | C19: =INDEX($C$15:$K$15, 1, MAX(C5 - Scenarios!$B$26, MIN(C5, 3))) * Scenarios!$B$20 + OFFSET(C19, 0, -1) -> 0 | D19: =INDEX($C$15:$K$15, 1, MAX(D5 - Scenarios!$B$26, MIN(D5, 3))) * Scenarios!$B$20 + OFFSET(D19, 0, -1) -> 0 | E19: =INDEX($C$15:$K$15, 1, MAX(E5 - Scenarios!$B$26, MIN(E5, 3))) * Scenarios!$B$20 + OFFSET(E19, 0, -1) -> 90 | F19: =INDEX($C$15:$K$15, 1, MAX(F5 - Scenarios!$B$26, MIN(F5, 3))) * Scenarios!$B$20 + OFFSET(F19, 0, -1) -> 360 | G19: =INDEX($C$15:$K$15, 1, MAX(G5 - Scenarios!$B$26, MIN(G5, 3))) * Scenarios!$B$20 + OFFSET(G19, 0, -1) -> 1851 | H19: =INDEX($C$15:$K$15, 1, MAX(H5 - Scenarios!$B$26, MIN(H5, 3))) * Scenarios!$B$20 + OFFSET(H19, 0, -1) -> 5005 | I19: =INDEX($C$15:$K$15, 1, MAX(I5 - Scenarios!$B$26, MIN(I5, 3))) * Scenarios!$B$20 + OFFSET(I19, 0, -1) -> 12580 | L19: headsets
A21: 2. HARDWARE PRICING
A22: Hardware ASP | C22: 300 | D22: 300 | E22: 300 | F22: 300 | G22: 300 | H22: 300 | I22: 300 | L22: £/unit | M22: ch.9 §9.4: mid of £250–350 range; allow time-varying
A23: Returns allowance | B23: 0.02 | L23: % of hardware revenue | M23: ch.9 §Warranty and Returns: DOA + trial-period returns only; in-warranty repairs covered separately by warranty provision
A24: 3. GTM CHANNEL MIX, SUBSCRIPTION & MARKETING SPLIT
A26: Headsets per institutional buyer | B26: 3 | L26: headsets/buyer | M26: ch.10 §10.2: schools/clubs each cover multiple sports
A27: Subscription price per headset | B27: 600 | L27: £/headset/yr | M27: ch.10 §10.2: flat £600/yr; per-headset billing
A28: Institutional buyers (schools + clubs) | C28: 0 | D28: 0 | E28: 30 | F28: 90 | G28: 150 | H28: 400 | I28: 750 | L28: buyers | M28: ch.10 §10.2 (Phase 2 paid + Phase 3 institutional, scaling through Y7)
A29: DTC buyers (direct-to-consumer, no subscription) | C29: 0 | D29: 0 | E29: 0 | F29: 0 | G29: 1041 | H29: 1954 | I29: 5325 | L29: buyers | M29: ch.10 §10.3 (3% / 4% / 6% conversion ramp on effective exposure)
A30: Institutional channel marketing | C30: 5000 | D30: 10000 | E30: 25000 | F30: 50000 | G30: 50000 | H30: 75000 | I30: 100000 | L30: £/yr | M30: B2B sales floor: conferences, sales reps, materials
A31: DTC channel marketing | C31: 0 | D31: 0 | E31: 0 | F31: 0 | G31: 100000 | H31: 225000 | I31: 400000 | L31: £/yr | M31: Parent acquisition: digital, social, content marketing
A32: Subscription ARPU per headset | C32: =$B$27 * Scenarios!$B$28 -> 600 | D32: =$B$27 * Scenarios!$B$28 -> 600 | E32: =$B$27 * Scenarios!$B$28 -> 600 | F32: =$B$27 * Scenarios!$B$28 -> 600 | G32: =$B$27 * Scenarios!$B$28 -> 600 | H32: =$B$27 * Scenarios!$B$28 -> 600 | I32: =$B$27 * Scenarios!$B$28 -> 600 | L32: £/sub/yr | M32: = $B$27 × ARPU scenario multiplier
A33: Subscription attach (per institutional headset) | B33: 1 | L33: % of inst. headsets | M33: 100% by construction; DTC excluded in row 17 by using delayed_inst
A34: 4. OTHER REVENUE LINES (toggle on/off)
A35: Research licences (1 = on, 0 = off) | B35: 0
A36: Research licence sites per year | C36: 2 | D36: 5 | E36: 8 | F36: 10 | G36: 12 | H36: 14 | I36: 15 | L36: sites
A37: Research licence £ per site per year | B37: 3000 | L37: £/site/yr
A38: Accessories & consumables (1 = on, 0 = off) | B38: 0
A39: Accessories £/yr per active subscriber | B39: 20 | L39: £/sub/yr | M39: Wipes, replacement facial interfaces, straps
A40: Accessories gross margin % | B40: 0.6 | L40: % | M40: Markup on consumables; assumed similar to medical disposables
A41: Extended warranty (1 = on, 0 = off) | B41: 0
A42: Extended warranty attach % at point of sale | B42: 0.15 | L42: %
A43: Extended warranty £ per attached unit | B43: 45 | L43: £/unit
A44: Extended warranty gross margin % | B44: 0.45 | L44: % | M44: ch.9 §9.5: 40–50% range
A45: 5. COST OF GOODS SOLD
A46: Unit cost — P1 (~10 units) | B46: 340 | L46: £/unit | M46: ch.9 tab:unit-cost-stack P1 midpoint (305-380)
A47: Unit cost — P2 (~500 units) | B47: 285 | L47: £/unit | M47: ch.9 tab:unit-cost-stack P2 midpoint (252-318)
A48: Unit cost — P3 (~10k units, RK3588S migration) | B48: 174 | L48: £/unit | M48: ch.9 tab:unit-cost-stack P3 midpoint (138-209)
A49: Effective unit cost per year | C49: =CHOOSE(C7, $B$46, $B$47, $B$48) * Scenarios!$B$21 -> 340 | D49: =CHOOSE(D7, $B$46, $B$47, $B$48) * Scenarios!$B$21 -> 340 | E49: =CHOOSE(E7, $B$46, $B$47, $B$48) * Scenarios!$B$21 -> 285 | F49: =CHOOSE(F7, $B$46, $B$47, $B$48) * Scenarios!$B$21 -> 285 | G49: =CHOOSE(G7, $B$46, $B$47, $B$48) * Scenarios!$B$21 -> 174 | H49: =CHOOSE(H7, $B$46, $B$47, $B$48) * Scenarios!$B$21 -> 174 | I49: =CHOOSE(I7, $B$46, $B$47, $B$48) * Scenarios!$B$21 -> 174 | L49: £/unit | M49: CHOOSE(phase, P1, P2, P3) × BOM scenario multiplier
A50: Subscription COGS as % of subscription revenue | B50: 0.15 | L50: % | M50: hosting, support tooling, data egress
A52: 6. HEADCOUNT & PAYROLL
A53: Role | B53: Salary £/yr | C53: FTE Y1 | D53: FTE Y2 | E53: FTE Y3 | F53: FTE Y4 | G53: FTE Y5 | H53: FTE Y6 | I53: FTE Y7
A54: CEO / commercial lead | B54: 50000 | C54: 1 | D54: 1 | E54: 1 | F54: 1 | G54: 1 | H54: 1 | I54: 1
A55: Engineering (HW / firmware / CV) | B55: 55000 | C55: 3 | D55: 3 | E55: 4 | F55: 5 | G55: 6 | H55: 7 | I55: 8
A56: Regulatory & quality | B56: 65000 | C56: 0 | D56: 0.5 | E56: 1 | F56: 1.5 | G56: 2 | H56: 2 | I56: 2
A57: Clinical research | B57: 40000 | C57: 0 | D57: 0.5 | E57: 1 | F57: 1 | G57: 1 | H57: 1 | I57: 1
A58: Sales / business development | B58: 48000 | C58: 0 | D58: 0 | E58: 1 | F58: 2 | G58: 3 | H58: 3 | I58: 3
A59: Operations / supply chain | B59: 45000 | C59: 0 | D59: 0 | E59: 0 | F59: 1 | G59: 1 | H59: 1 | I59: 1
A60: Customer support | B60: 32000 | C60: 0 | D60: 0 | E60: 0 | F60: 0.5 | G60: 1 | H60: 1.5 | I60: 2
A61: (spare slot) | B61: 0 | C61: 0 | D61: 0 | E61: 0 | F61: 0 | G61: 0 | H61: 0 | I61: 0
A62: Total FTE | C62: =SUM(C54:C61) -> 4 | D62: =SUM(D54:D61) -> 5 | E62: =SUM(E54:E61) -> 8 | F62: =SUM(F54:F61) -> 12 | G62: =SUM(G54:G61) -> 15 | H62: =SUM(H54:H61) -> 16.5 | I62: =SUM(I54:I61) -> 18
A63: Base payroll (cash salaries) | C63: =SUMPRODUCT($B$54:$B$61, C54:C61) -> 215000 | D63: =SUMPRODUCT($B$54:$B$61, D54:D61) -> 267500 | E63: =SUMPRODUCT($B$54:$B$61, E54:E61) -> 423000 | F63: =SUMPRODUCT($B$54:$B$61, F54:F61) -> 619500 | G63: =SUMPRODUCT($B$54:$B$61, G54:G61) -> 771000 | H63: =SUMPRODUCT($B$54:$B$61, H54:H61) -> 842000 | I63: =SUMPRODUCT($B$54:$B$61, I54:I61) -> 913000 | L63: £
A64: Founder cash adjustment | C64: -30000 | D64: -30000 | E64: 0 | F64: 0 | G64: 0 | H64: 0 | I64: 0 | L64: £ | M64: Negative = founders take partial cash; affects P1–P2 only
A65: On-cost loading % | B65: 0.19 | L65: % | M65: ch.9 §9.5: NI 12–14% + pension 3% + benefits ~2%
A66: Loaded payroll (incl. on-cost) | C66: =(C63 + C64) * (1 + $B$65) * Scenarios!$B$23 -> 220150 | D66: =(D63 + D64) * (1 + $B$65) * Scenarios!$B$23 -> 282625 | E66: =(E63 + E64) * (1 + $B$65) * Scenarios!$B$23 -> 503370 | F66: =(F63 + F64) * (1 + $B$65) * Scenarios!$B$23 -> 737205 | G66: =(G63 + G64) * (1 + $B$65) * Scenarios!$B$23 -> 917490 | H66: =(H63 + H64) * (1 + $B$65) * Scenarios!$B$23 -> 1001980 | I66: =(I63 + I64) * (1 + $B$65) * Scenarios!$B$23 -> 1086470 | L66: £ | M66: (base + founder adj) × (1 + on-cost) × payroll scenario multiplier
A67: Sales commission % | B67: 0.15 | L67: % of new ARR | M67: Applied to gross new subscription revenue
A68: Sales commission £ | C68: =INDEX($C$28:$K$28, 1, MAX(C5 - Scenarios!$B$26, MIN(C5, 3))) * $B$26 * Scenarios!$B$20 * $B$33 * C32 * $B$67 -> 0 | D68: =INDEX($C$28:$K$28, 1, MAX(D5 - Scenarios!$B$26, MIN(D5, 3))) * $B$26 * Scenarios!$B$20 * $B$33 * D32 * $B$67 -> 0 | E68: =INDEX($C$28:$K$28, 1, MAX(E5 - Scenarios!$B$26, MIN(E5, 3))) * $B$26 * Scenarios!$B$20 * $B$33 * E32 * $B$67 -> 8100 | F68: =INDEX($C$28:$K$28, 1, MAX(F5 - Scenarios!$B$26, MIN(F5, 3))) * $B$26 * Scenarios!$B$20 * $B$33 * F32 * $B$67 -> 24300 | G68: =INDEX($C$28:$K$28, 1, MAX(G5 - Scenarios!$B$26, MIN(G5, 3))) * $B$26 * Scenarios!$B$20 * $B$33 * G32 * $B$67 -> 40500 | H68: =INDEX($C$28:$K$28, 1, MAX(H5 - Scenarios!$B$26, MIN(H5, 3))) * $B$26 * Scenarios!$B$20 * $B$33 * H32 * $B$67 -> 108000 | I68: =INDEX($C$28:$K$28, 1, MAX(I5 - Scenarios!$B$26, MIN(I5, 3))) * $B$26 * Scenarios!$B$20 * $B$33 * I32 * $B$67 -> 202500 | L68: £ | M68: institutional buyers × headsets/inst × adoption × attach × ARPU × commission %
A69: Total people cost | C69: =C66 + C68 -> 220150 | D69: =D66 + D68 -> 282625 | E69: =E66 + E68 -> 511470 | F69: =F66 + F68 -> 761505 | G69: =G66 + G68 -> 957990 | H69: =H66 + H68 -> 1109980 | I69: =I66 + I68 -> 1288970 | L69: £ | M69: = loaded payroll + sales commission
A71: 7. OTHER OPERATING EXPENSES
A72: R&D non-payroll | C72: 15000 | D72: 20000 | E72: 25000 | F72: 30000 | G72: 30000 | H72: 30000 | I72: 30000 | L72: £ | M72: Prototyping components, dev tools, CAD/sim licences
A73: Marketing (derived) | C73: =C30 + C31 -> 5000 | D73: =D30 + D31 -> 10000 | E73: =E30 + E31 -> 25000 | F73: =F30 + F31 -> 50000 | G73: =G30 + G31 -> 150000 | H73: =H30 + H31 -> 300000 | I73: =I30 + I31 -> 500000 | L73: £ | M73: = institutional channel marketing + DTC channel marketing (rows 30 + 31)
A74: Travel & subsistence | C74: 8000 | D74: 12000 | E74: 25000 | F74: 40000 | G74: 55000 | H74: 70000 | I74: 85000 | L74: £
A75: Professional fees | C75: 10000 | D75: 15000 | E75: 30000 | F75: 40000 | G75: 50000 | H75: 60000 | I75: 70000 | L75: £ | M75: Legal, accounting, IP, audit
A76: IT and software, cloud infrastructure | C76: 6000 | D76: 10000 | E76: 20000 | F76: 35000 | G76: 55000 | H76: 75000 | I76: 95000 | L76: £ | M76: SaaS licences, dev infrastructure, cloud hosting (scales with installed base)
A77: Total other opex | C77: =SUM(C72:C76) -> 44000 | D77: =SUM(D72:D76) -> 67000 | E77: =SUM(E72:E76) -> 125000 | F77: =SUM(F72:F76) -> 195000 | G77: =SUM(G72:G76) -> 340000 | H77: =SUM(H72:H76) -> 535000 | I77: =SUM(I72:I76) -> 780000 | L77: £
A79: 8. FACILITIES
A80: Facilities annual cost | C80: 0 | D80: 20000 | E80: 24000 | F80: 35000 | G80: 45000 | H80: 55000 | I80: 65000 | L80: £ | M80: ch.9 §9.5: free incubator → coworking → office
A82: 9. INSURANCE
A83: Insurance annual cost | C83: 6000 | D83: 12000 | E83: 20000 | F83: 28000 | G83: 36000 | H83: 44000 | I83: 50000 | L83: £ | M83: ch.9 tab:ent-ops-insurance — phased programme
A85: 10. REGULATORY & CLINICAL [PROVISIONAL → ch.7]
A86: One-off regulatory & clinical (UKCA route) | C86: 0 | D86: 130000 | E86: 140000 | F86: 0 | G86: 0 | H86: 0 | I86: 0 | L86: £ | M86: QMS + biocompat + EMC + NB fees + clinical investigation
A87: Ongoing post-market & NB surveillance | C87: 0 | D87: 0 | E87: 0 | F87: 55000 | G87: 55000 | H87: 60000 | I87: 65000 | L87: £ | M87: PMS, periodic safety updates, NB annual surveillance
A88: Total regulatory & clinical | C88: =C86 + C87 -> 0 | D88: =D86 + D87 -> 130000 | E88: =E86 + E87 -> 140000 | F88: =F86 + F87 -> 55000 | G88: =G86 + G87 -> 55000 | H88: =H86 + H87 -> 60000 | I88: =I86 + I87 -> 65000 | L88: £
A90: 11. CAPEX & DEPRECIATION
A91: Capex item | B91: Amount £ | C91: Period | D91: Life (yrs)
A92: Bench equipment, ESD, basic instruments | B92: 4000 | C92: 1 | D92: 5
A93: Desktop 3D printer + accessories | B93: 2500 | C93: 1 | D93: 5
A94: Optical alignment fixtures (in-house) | B94: 6000 | C94: 2 | D94: 5
A95: Test fixtures (formal, jig-assisted) | B95: 15000 | C95: 3 | D95: 5
A96: Office fit-out (lab area, desks, security) | B96: 20000 | C96: 4 | D96: 5
A97: Aluminium injection moulding tool | B97: 12000 | C97: 5 | D97: 5
A98: Calibration jigs for contract manufacturer | B98: 18000 | C98: 5 | D98: 5
A99: End-of-line test rig upgrade | B99: 12000 | C99: 6 | D99: 5
A100: Steel injection moulding tool | B100: 22000 | C100: 7 | D100: 7
A101: (spare slot) | B101: 0 | C101: 1 | D101: 5
A103: Capex per year | C103: =SUMIFS($B$92:$B$101, $C$92:$C$101, C5) -> 6500 | D103: =SUMIFS($B$92:$B$101, $C$92:$C$101, D5) -> 6000 | E103: =SUMIFS($B$92:$B$101, $C$92:$C$101, E5) -> 15000 | F103: =SUMIFS($B$92:$B$101, $C$92:$C$101, F5) -> 20000 | G103: =SUMIFS($B$92:$B$101, $C$92:$C$101, G5) -> 30000 | H103: =SUMIFS($B$92:$B$101, $C$92:$C$101, H5) -> 12000 | I103: =SUMIFS($B$92:$B$101, $C$92:$C$101, I5) -> 22000 | L103: £
A104: Cumulative capex | C104: =C103 + OFFSET(C104, 0, -1) -> 6500 | D104: =D103 + OFFSET(D104, 0, -1) -> 12500 | E104: =E103 + OFFSET(E104, 0, -1) -> 27500 | F104: =F103 + OFFSET(F104, 0, -1) -> 47500 | G104: =G103 + OFFSET(G104, 0, -1) -> 77500 | H104: =H103 + OFFSET(H104, 0, -1) -> 89500 | I104: =I103 + OFFSET(I104, 0, -1) -> 111500 | L104: £
A105: Depreciation per year | C105: =SUMPRODUCT(($C$92:$C$101 <= C5) * (C5 < $C$92:$C$101 + $D$92:$D$101) * ($B$92:$B$101 / $D$92:$D$101)) -> 1300 | D105: =SUMPRODUCT(($C$92:$C$101 <= D5) * (D5 < $C$92:$C$101 + $D$92:$D$101) * ($B$92:$B$101 / $D$92:$D$101)) -> 2500 | E105: =SUMPRODUCT(($C$92:$C$101 <= E5) * (E5 < $C$92:$C$101 + $D$92:$D$101) * ($B$92:$B$101 / $D$92:$D$101)) -> 5500 | F105: =SUMPRODUCT(($C$92:$C$101 <= F5) * (F5 < $C$92:$C$101 + $D$92:$D$101) * ($B$92:$B$101 / $D$92:$D$101)) -> 9500 | G105: =SUMPRODUCT(($C$92:$C$101 <= G5) * (G5 < $C$92:$C$101 + $D$92:$D$101) * ($B$92:$B$101 / $D$92:$D$101)) -> 15500 | H105: =SUMPRODUCT(($C$92:$C$101 <= H5) * (H5 < $C$92:$C$101 + $D$92:$D$101) * ($B$92:$B$101 / $D$92:$D$101)) -> 16600 | I105: =SUMPRODUCT(($C$92:$C$101 <= I5) * (I5 < $C$92:$C$101 + $D$92:$D$101) * ($B$92:$B$101 / $D$92:$D$101)) -> 18542.857 | L105: £ | M105: Straight-line over each item's life, from period of acquisition
A106: Accumulated depreciation | C106: =C105 + OFFSET(C106, 0, -1) -> 1300 | D106: =D105 + OFFSET(D106, 0, -1) -> 3800 | E106: =E105 + OFFSET(E106, 0, -1) -> 9300 | F106: =F105 + OFFSET(F106, 0, -1) -> 18800 | G106: =G105 + OFFSET(G106, 0, -1) -> 34300 | H106: =H105 + OFFSET(H106, 0, -1) -> 50900 | I106: =I105 + OFFSET(I106, 0, -1) -> 69442.857 | L106: £
A107: Net PP&E | C107: =C104 - C106 -> 5200 | D107: =D104 - D106 -> 8700 | E107: =E104 - E106 -> 18200 | F107: =F104 - F106 -> 28700 | G107: =G104 - G106 -> 43200 | H107: =H104 - H106 -> 38600 | I107: =I104 - I106 -> 42057.143 | L107: £ | M107: = cumulative capex − accumulated depreciation
A109: 12. WORKING CAPITAL ASSUMPTIONS
A110: Inventory days (DIO, on COGS) | B110: 75 | L110: days
A111: Receivable days (DSO, on revenue) | B111: 45 | L111: days
A112: Payable days (DPO, on COGS + opex ex-payroll) | B112: 45 | L112: days
A113: Warranty provision % of hardware revenue | B113: 0.03 | L113: % | M113: ch.9 §9.5: 2–5% range
...

Sheet Unit economics
A1: Unit Economics — Per-customer profitability
A2: All values driven from the Assumptions tab. Y6–Y7 are the steady-state reference (P3 mature, post-breakeven).
A4: Year | C4: =Assumptions!C4 -> Y1 | D4: =Assumptions!D4 -> Y2 | E4: =Assumptions!E4 -> Y3 | F4: =Assumptions!F4 -> Y4 | G4: =Assumptions!G4 -> Y5 | H4: =Assumptions!H4 -> Y6 | I4: =Assumptions!I4 -> Y7
A5: Period number | C5: =Assumptions!C5 -> 1 | D5: =Assumptions!D5 -> 2 | E5: =Assumptions!E5 -> 3 | F5: =Assumptions!F5 -> 4 | G5: =Assumptions!G5 -> 5 | H5: =Assumptions!H5 -> 6 | I5: =Assumptions!I5 -> 7
A6: Phase | C6: =Assumptions!C7 -> 1 | D6: =Assumptions!D7 -> 1 | E6: =Assumptions!E7 -> 2 | F6: =Assumptions!F7 -> 2 | G6: =Assumptions!G7 -> 3 | H6: =Assumptions!H7 -> 3 | I6: =Assumptions!I7 -> 3
A8: 1. HARDWARE ECONOMICS (per unit)
A9: Hardware ASP | C9: =Assumptions!C22 -> 300 | D9: =Assumptions!D22 -> 300 | E9: =Assumptions!E22 -> 300 | F9: =Assumptions!F22 -> 300 | G9: =Assumptions!G22 -> 300 | H9: =Assumptions!H22 -> 300 | I9: =Assumptions!I22 -> 300 | L9: £/unit
A10: Effective unit cost | C10: =Assumptions!C49 -> 340 | D10: =Assumptions!D49 -> 340 | E10: =Assumptions!E49 -> 285 | F10: =Assumptions!F49 -> 285 | G10: =Assumptions!G49 -> 174 | H10: =Assumptions!H49 -> 174 | I10: =Assumptions!I49 -> 174 | L10: £/unit
A11: Hardware contribution per unit | C11: =C9 - C10 -> -40 | D11: =D9 - D10 -> -40 | E11: =E9 - E10 -> 15 | F11: =F9 - F10 -> 15 | G11: =G9 - G10 -> 126 | H11: =H9 - H10 -> 126 | I11: =I9 - I10 -> 126 | L11: £/unit
A12: Hardware gross margin % | C12: =IFERROR(C11/C9, 0) -> -0.13333333 | D12: =IFERROR(D11/D9, 0) -> -0.13333333 | E12: =IFERROR(E11/E9, 0) -> 0.05 | F12: =IFERROR(F11/F9, 0) -> 0.05 | G12: =IFERROR(G11/G9, 0) -> 0.42 | H12: =IFERROR(H11/H9, 0) -> 0.42 | I12: =IFERROR(I11/I9, 0) -> 0.42 | L12: %
A14: 2. SUBSCRIPTION ECONOMICS (per active customer per year)
A15: Blended ARPU | C15: =Assumptions!C32 -> 600 | D15: =Assumptions!D32 -> 600 | E15: =Assumptions!E32 -> 600 | F15: =Assumptions!F32 -> 600 | G15: =Assumptions!G32 -> 600 | H15: =Assumptions!H32 -> 600 | I15: =Assumptions!I32 -> 600 | L15: £/sub/yr
A16: Subscription COGS rate | C16: =Assumptions!$B$50 -> 0.15 | D16: =Assumptions!$B$50 -> 0.15 | E16: =Assumptions!$B$50 -> 0.15 | F16: =Assumptions!$B$50 -> 0.15 | G16: =Assumptions!$B$50 -> 0.15 | H16: =Assumptions!$B$50 -> 0.15 | I16: =Assumptions!$B$50 -> 0.15 | L16: %
A17: Subscription contribution | C17: =C15 * (1 - C16) -> 510 | D17: =D15 * (1 - D16) -> 510 | E17: =E15 * (1 - E16) -> 510 | F17: =F15 * (1 - F16) -> 510 | G17: =G15 * (1 - G16) -> 510 | H17: =H15 * (1 - H16) -> 510 | I17: =I15 * (1 - I16) -> 510 | L17: £/sub/yr
A18: Subscription gross margin % | C18: =IFERROR(C17/C15, 0) -> 0.85 | D18: =IFERROR(D17/D15, 0) -> 0.85 | E18: =IFERROR(E17/E15, 0) -> 0.85 | F18: =IFERROR(F17/F15, 0) -> 0.85 | G18: =IFERROR(G17/G15, 0) -> 0.85 | H18: =IFERROR(H17/H15, 0) -> 0.85 | I18: =IFERROR(I17/I15, 0) -> 0.85 | L18: %
A20: 3. ACCESSORIES & CONSUMABLES (per active customer per year)
A21: Accessories enabled (1 = on, 0 = off) | C21: =Assumptions!$B$38 -> 0 | D21: =Assumptions!$B$38 -> 0 | E21: =Assumptions!$B$38 -> 0 | F21: =Assumptions!$B$38 -> 0 | G21: =Assumptions!$B$38 -> 0 | H21: =Assumptions!$B$38 -> 0 | I21: =Assumptions!$B$38 -> 0
A22: Accessories revenue per active sub | C22: =C21 * Assumptions!$B$39 -> 0 | D22: =D21 * Assumptions!$B$39 -> 0 | E22: =E21 * Assumptions!$B$39 -> 0 | F22: =F21 * Assumptions!$B$39 -> 0 | G22: =G21 * Assumptions!$B$39 -> 0 | H22: =H21 * Assumptions!$B$39 -> 0 | I22: =I21 * Assumptions!$B$39 -> 0 | L22: £/sub/yr
A23: Accessories gross margin % | C23: =Assumptions!$B$40 -> 0.6 | D23: =Assumptions!$B$40 -> 0.6 | E23: =Assumptions!$B$40 -> 0.6 | F23: =Assumptions!$B$40 -> 0.6 | G23: =Assumptions!$B$40 -> 0.6 | H23: =Assumptions!$B$40 -> 0.6 | I23: =Assumptions!$B$40 -> 0.6 | L23: %
A24: Accessories contribution per active sub | C24: =C22 * C23 -> 0 | D24: =D22 * D23 -> 0 | E24: =E22 * E23 -> 0 | F24: =F22 * F23 -> 0 | G24: =G22 * G23 -> 0 | H24: =H22 * H23 -> 0 | I24: =I22 * I23 -> 0 | L24: £/sub/yr
A26: 4. EXTENDED WARRANTY (one-off, per new customer at sale)
A27: Warranty enabled (1 = on, 0 = off) | C27: =Assumptions!$B$41 -> 0 | D27: =Assumptions!$B$41 -> 0 | E27: =Assumptions!$B$41 -> 0 | F27: =Assumptions!$B$41 -> 0 | G27: =Assumptions!$B$41 -> 0 | H27: =Assumptions!$B$41 -> 0 | I27: =Assumptions!$B$41 -> 0
A28: Attach % at sale | C28: =Assumptions!$B$42 -> 0.15 | D28: =Assumptions!$B$42 -> 0.15 | E28: =Assumptions!$B$42 -> 0.15 | F28: =Assumptions!$B$42 -> 0.15 | G28: =Assumptions!$B$42 -> 0.15 | H28: =Assumptions!$B$42 -> 0.15 | I28: =Assumptions!$B$42 -> 0.15 | L28: %
A29: Warranty £ per attached unit | C29: =Assumptions!$B$43 -> 45 | D29: =Assumptions!$B$43 -> 45 | E29: =Assumptions!$B$43 -> 45 | F29: =Assumptions!$B$43 -> 45 | G29: =Assumptions!$B$43 -> 45 | H29: =Assumptions!$B$43 -> 45 | I29: =Assumptions!$B$43 -> 45 | L29: £
A30: Warranty gross margin % | C30: =Assumptions!$B$44 -> 0.45 | D30: =Assumptions!$B$44 -> 0.45 | E30: =Assumptions!$B$44 -> 0.45 | F30: =Assumptions!$B$44 -> 0.45 | G30: =Assumptions!$B$44 -> 0.45 | H30: =Assumptions!$B$44 -> 0.45 | I30: =Assumptions!$B$44 -> 0.45 | L30: %
A31: Warranty contribution per new unit | C31: =C27 * C28 * C29 * C30 -> 0 | D31: =D27 * D28 * D29 * D30 -> 0 | E31: =E27 * E28 * E29 * E30 -> 0 | F31: =F27 * F28 * F29 * F30 -> 0 | G31: =G27 * G28 * G29 * G30 -> 0 | H31: =H27 * H28 * H29 * H30 -> 0 | I31: =I27 * I28 * I29 * I30 -> 0 | L31: £/unit
A33: 5. TOTAL ANNUAL ECONOMICS (per active customer)
A34: Total annual revenue per active customer | C34: =C15 + C22 -> 600 | D34: =D15 + D22 -> 600 | E34: =E15 + E22 -> 600 | F34: =F15 + F22 -> 600 | G34: =G15 + G22 -> 600 | H34: =H15 + H22 -> 600 | I34: =I15 + I22 -> 600 | L34: £/sub/yr | M34: = ARPU + accessories revenue
A35: Total annual contribution per active customer | C35: =C17 + C24 -> 510 | D35: =D17 + D24 -> 510 | E35: =E17 + E24 -> 510 | F35: =F17 + F24 -> 510 | G35: =G17 + G24 -> 510 | H35: =H17 + H24 -> 510 | I35: =I17 + I24 -> 510 | L35: £/sub/yr | M35: = sub contribution + accessories contribution
A37: 6. CUSTOMER LIFETIME VALUE (LTV)
A38: Annual subscription churn | C38: =Assumptions!$B$16 -> 0.1 | D38: =Assumptions!$B$16 -> 0.1 | E38: =Assumptions!$B$16 -> 0.1 | F38: =Assumptions!$B$16 -> 0.1 | G38: =Assumptions!$B$16 -> 0.1 | H38: =Assumptions!$B$16 -> 0.1 | I38: =Assumptions!$B$16 -> 0.1 | L38: %
A39: Implied avg customer lifetime | C39: =IFERROR(1/C38, 0) -> 10 | D39: =IFERROR(1/D38, 0) -> 10 | E39: =IFERROR(1/E38, 0) -> 10 | F39: =IFERROR(1/F38, 0) -> 10 | G39: =IFERROR(1/G38, 0) -> 10 | H39: =IFERROR(1/H38, 0) -> 10 | I39: =IFERROR(1/I38, 0) -> 10 | L39: years | M39: = 1 / churn (perpetuity equivalent)
A40: 3-year LTV factor (sub side) | C40: =1 + (1-C38) + (1-C38)^2 -> 2.71 | D40: =1 + (1-D38) + (1-D38)^2 -> 2.71 | E40: =1 + (1-E38) + (1-E38)^2 -> 2.71 | F40: =1 + (1-F38) + (1-F38)^2 -> 2.71 | G40: =1 + (1-G38) + (1-G38)^2 -> 2.71 | H40: =1 + (1-H38) + (1-H38)^2 -> 2.71 | I40: =1 + (1-I38) + (1-I38)^2 -> 2.71 | L40: multiplier | M40: = 1 + (1−c) + (1−c)²
A41: 3-year sub + accessories LTV | C41: =C35 * C40 -> 1382.1 | D41: =D35 * D40 -> 1382.1 | E41: =E35 * E40 -> 1382.1 | F41: =F35 * F40 -> 1382.1 | G41: =G35 * G40 -> 1382.1 | H41: =H35 * H40 -> 1382.1 | I41: =I35 * I40 -> 1382.1 | L41: £/customer
A42: 3-year total LTV per customer | C42: =C11 + C31 + C41 -> 1342.1 | D42: =D11 + D31 + D41 -> 1342.1 | E42: =E11 + E31 + E41 -> 1397.1 | F42: =F11 + F31 + F41 -> 1397.1 | G42: =G11 + G31 + G41 -> 1508.1 | H42: =H11 + H31 + H41 -> 1508.1 | I42: =I11 + I31 + I41 -> 1508.1 | L42: £/customer | M42: = HW contribution + warranty contribution + 3-yr sub+acc LTV
A43: Steady-state sub + accessories LTV | C43: =IFERROR(C35/C38, 0) -> 5100 | D43: =IFERROR(D35/D38, 0) -> 5100 | E43: =IFERROR(E35/E38, 0) -> 5100 | F43: =IFERROR(F35/F38, 0) -> 5100 | G43: =IFERROR(G35/G38, 0) -> 5100 | H43: =IFERROR(H35/H38, 0) -> 5100 | I43: =IFERROR(I35/I38, 0) -> 5100 | L43: £/customer | M43: = annual contribution / churn (perpetuity)
A44: Steady-state total LTV per customer | C44: =C11 + C31 + C43 -> 5060 | D44: =D11 + D31 + D43 -> 5060 | E44: =E11 + E31 + E43 -> 5115 | F44: =F11 + F31 + F43 -> 5115 | G44: =G11 + G31 + G43 -> 5226 | H44: =H11 + H31 + H43 -> 5226 | I44: =I11 + I31 + I43 -> 5226 | L44: £/customer
A46: 7. CUSTOMER ACQUISITION COST (by channel)
A47: Institutional channel marketing | C47: =Assumptions!C30 -> 5000 | D47: =Assumptions!D30 -> 10000 | E47: =Assumptions!E30 -> 25000 | F47: =Assumptions!F30 -> 50000 | G47: =Assumptions!G30 -> 50000 | H47: =Assumptions!H30 -> 75000 | I47: =Assumptions!I30 -> 100000 | L47: £/yr
A48: Sales commission (institutional only) | C48: =Assumptions!C68 -> 0 | D48: =Assumptions!D68 -> 0 | E48: =Assumptions!E68 -> 8100 | F48: =Assumptions!F68 -> 24300 | G48: =Assumptions!G68 -> 40500 | H48: =Assumptions!H68 -> 108000 | I48: =Assumptions!I68 -> 202500 | L48: £/yr
A49: Institutional acquisition spend | C49: =C47 + C48 -> 5000 | D49: =D47 + D48 -> 10000 | E49: =E47 + E48 -> 33100 | F49: =F47 + F48 -> 74300 | G49: =G47 + G48 -> 90500 | H49: =H47 + H48 -> 183000 | I49: =I47 + I48 -> 302500 | L49: £/yr
A50: Institutional buyers | C50: =Assumptions!C28 -> 0 | D50: =Assumptions!D28 -> 0 | E50: =Assumptions!E28 -> 30 | F50: =Assumptions!F28 -> 90 | G50: =Assumptions!G28 -> 150 | H50: =Assumptions!H28 -> 400 | I50: =Assumptions!I28 -> 750 | L50: buyers
A51: CAC per institutional customer | C51: =IFERROR(C49/C50, 0) -> 0 | D51: =IFERROR(D49/D50, 0) -> 0 | E51: =IFERROR(E49/E50, 0) -> 1103.3333 | F51: =IFERROR(F49/F50, 0) -> 825.55556 | G51: =IFERROR(G49/G50, 0) -> 603.33333 | H51: =IFERROR(H49/H50, 0) -> 457.5 | I51: =IFERROR(I49/I50, 0) -> 403.33333 | L51: £/customer | M51: = institutional acquisition spend / institutional buyers
A52: DTC channel marketing | C52: =Assumptions!C31 -> 0 | D52: =Assumptions!D31 -> 0 | E52: =Assumptions!E31 -> 0 | F52: =Assumptions!F31 -> 0 | G52: =Assumptions!G31 -> 100000 | H52: =Assumptions!H31 -> 225000 | I52: =Assumptions!I31 -> 400000 | L52: £/yr
A53: DTC buyers | C53: =Assumptions!C29 -> 0 | D53: =Assumptions!D29 -> 0 | E53: =Assumptions!E29 -> 0 | F53: =Assumptions!F29 -> 0 | G53: =Assumptions!G29 -> 1041 | H53: =Assumptions!H29 -> 1954 | I53: =Assumptions!I29 -> 5325 | L53: buyers
A54: CAC per DTC customer | C54: =IFERROR(C52/C53, 0) -> 0 | D54: =IFERROR(D52/D53, 0) -> 0 | E54: =IFERROR(E52/E53, 0) -> 0 | F54: =IFERROR(F52/F53, 0) -> 0 | G54: =IFERROR(G52/G53, 0) -> 96.061479 | H54: =IFERROR(H52/H53, 0) -> 115.14841 | I54: =IFERROR(I52/I53, 0) -> 75.117371 | L54: £/customer | M54: = DTC marketing / DTC buyers (no commission on DTC)
A56: 8. LTV PER CUSTOMER & LTV : CAC (by channel)
A57: 3-year LTV per institutional customer | C57: =Assumptions!$B$26 * (C11 + C41) -> 4026.3 | D57: =Assumptions!$B$26 * (D11 + D41) -> 4026.3 | E57: =Assumptions!$B$26 * (E11 + E41) -> 4191.3 | F57: =Assumptions!$B$26 * (F11 + F41) -> 4191.3 | G57: =Assumptions!$B$26 * (G11 + G41) -> 4524.3 | H57: =Assumptions!$B$26 * (H11 + H41) -> 4524.3 | I57: =Assumptions!$B$26 * (I11 + I41) -> 4524.3 | L57: £/customer | M57: = 3 headsets × (HW contribution + 3-yr sub LTV per headset)
A58: LTV per DTC customer (one-off) | C58: =C11 -> -40 | D58: =D11 -> -40 | E58: =E11 -> 15 | F58: =F11 -> 15 | G58: =G11 -> 126 | H58: =H11 -> 126 | I58: =I11 -> 126 | L58: £/customer | M58: = hardware contribution per headset (no subscription)
A59: LTV : CAC ratio (institutional, 3-year) | C59: =IFERROR(C57/C51, 0) -> 0 | D59: =IFERROR(D57/D51, 0) -> 0 | E59: =IFERROR(E57/E51, 0) -> 3.7987613 | F59: =IFERROR(F57/F51, 0) -> 5.0769448 | G59: =IFERROR(G57/G51, 0) -> 7.4988398 | H59: =IFERROR(H57/H51, 0) -> 9.8891803 | I59: =IFERROR(I57/I51, 0) -> 11.217273 | L59: ratio | M59: Industry benchmark > 3.0x
A60: LTV : CAC ratio (DTC) | C60: =IFERROR(C58/C54, 0) -> 0 | D60: =IFERROR(D58/D54, 0) -> 0 | E60: =IFERROR(E58/E54, 0) -> 0 | F60: =IFERROR(F58/F54, 0) -> 0 | G60: =IFERROR(G58/G54, 0) -> 1.31166 | H60: =IFERROR(H58/H54, 0) -> 1.09424 | I60: =IFERROR(I58/I54, 0) -> 1.677375 | L60: ratio | M60: DTC must clear 1.0x to be self-funding at acquisition
A61: Payback period (institutional) | C61: =IFERROR(C51*12/(Assumptions!$B$26 * C35), 0) -> 0 | D61: =IFERROR(D51*12/(Assumptions!$B$26 * D35), 0) -> 0 | E61: =IFERROR(E51*12/(Assumptions!$B$26 * E35), 0) -> 8.6535948 | F61: =IFERROR(F51*12/(Assumptions!$B$26 * F35), 0) -> 6.4749455 | G61: =IFERROR(G51*12/(Assumptions!$B$26 * G35), 0) -> 4.7320261 | H61: =IFERROR(H51*12/(Assumptions!$B$26 * H35), 0) -> 3.5882353 | I61: =IFERROR(I51*12/(Assumptions!$B$26 * I35), 0) -> 3.1633987 | L61: months | M61: = CAC × 12 / annual contribution per institutional customer (3 headsets)
A63: 9. STEADY-STATE SUMMARY (Y7 reference)
A64: Hardware contribution per headset | B64: =K11 -> 0
A65: Subscription contribution per headset/yr | B65: =K17 -> 0
A66: 3-year LTV per institutional customer | B66: =K57 -> 0
A67: LTV per DTC customer (hardware only) | B67: =K58 -> 0
A68: CAC per institutional customer | B68: =K51 -> 0
A69: CAC per DTC customer | B69: =K54 -> 0
A70: LTV : CAC (institutional, 3-year) | B70: =K59 -> 0
A71: LTV : CAC (DTC) | B71: =K60 -> 0
A72: Payback period (institutional, months) | B72: =K61 -> 0

Sheet P&L
A1: Profit & Loss — 7-year projection
A2: Driven from the Assumptions tab. Read the EBITDA line for the headline shape; read R&D credit + corp tax for the cash impact of loss-making years.
A4: Year | C4: =Assumptions!C4 -> Y1 | D4: =Assumptions!D4 -> Y2 | E4: =Assumptions!E4 -> Y3 | F4: =Assumptions!F4 -> Y4 | G4: =Assumptions!G4 -> Y5 | H4: =Assumptions!H4 -> Y6 | I4: =Assumptions!I4 -> Y7
A5: Period number | C5: =Assumptions!C5 -> 1 | D5: =Assumptions!D5 -> 2 | E5: =Assumptions!E5 -> 3 | F5: =Assumptions!F5 -> 4 | G5: =Assumptions!G5 -> 5 | H5: =Assumptions!H5 -> 6 | I5: =Assumptions!I5 -> 7
A6: Phase | C6: =Assumptions!C7 -> 1 | D6: =Assumptions!D7 -> 1 | E6: =Assumptions!E7 -> 2 | F6: =Assumptions!F7 -> 2 | G6: =Assumptions!G7 -> 3 | H6: =Assumptions!H7 -> 3 | I6: =Assumptions!I7 -> 3
A8: 1. REVENUE
A9: Hardware revenue | C9: =INDEX(Assumptions!$C$15:$K$15, 1, MAX(C5 - Scenarios!$B$26, MIN(C5, 3))) * Scenarios!$B$20 * Assumptions!C22 * Scenarios!$B$27 * (1 - Assumptions!$B$23) -> 0 | D9: =INDEX(Assumptions!$C$15:$K$15, 1, MAX(D5 - Scenarios!$B$26, MIN(D5, 3))) * Scenarios!$B$20 * Assumptions!D22 * Scenarios!$B$27 * (1 - Assumptions!$B$23) -> 0 | E9: =INDEX(Assumptions!$C$15:$K$15, 1, MAX(E5 - Scenarios!$B$26, MIN(E5, 3))) * Scenarios!$B$20 * Assumptions!E22 * Scenarios!$B$27 * (1 - Assumptions!$B$23) -> 26460 | F9: =INDEX(Assumptions!$C$15:$K$15, 1, MAX(F5 - Scenarios!$B$26, MIN(F5, 3))) * Scenarios!$B$20 * Assumptions!F22 * Scenarios!$B$27 * (1 - Assumptions!$B$23) -> 79380 | G9: =INDEX(Assumptions!$C$15:$K$15, 1, MAX(G5 - Scenarios!$B$26, MIN(G5, 3))) * Scenarios!$B$20 * Assumptions!G22 * Scenarios!$B$27 * (1 - Assumptions!$B$23) -> 438354 | H9: =INDEX(Assumptions!$C$15:$K$15, 1, MAX(H5 - Scenarios!$B$26, MIN(H5, 3))) * Scenarios!$B$20 * Assumptions!H22 * Scenarios!$B$27 * (1 - Assumptions!$B$23) -> 927276 | I9: =INDEX(Assumptions!$C$15:$K$15, 1, MAX(I5 - Scenarios!$B$26, MIN(I5, 3))) * Scenarios!$B$20 * Assumptions!I22 * Scenarios!$B$27 * (1 - Assumptions!$B$23) -> 2227050 | L9: £ | M9: delay-shifted new units × adoption × ASP × ASP scenario × (1 − returns allowance)
A10: Subscription revenue | C10: =Assumptions!C18 * Assumptions!C32 -> 0 | D10: =Assumptions!D18 * Assumptions!D32 -> 0 | E10: =Assumptions!E18 * Assumptions!E32 -> 27000 | F10: =Assumptions!F18 * Assumptions!F32 -> 132300 | G10: =Assumptions!G18 * Assumptions!G32 -> 335070 | H10: =Assumptions!H18 * Assumptions!H32 -> 796563 | I10: =Assumptions!I18 * Assumptions!I32 -> 1751906.7 | L10: £ | M10: average subscribers × blended ARPU
A11: Research licence revenue | C11: =Assumptions!$B$35 * Assumptions!C36 * Assumptions!$B$37 -> 0 | D11: =Assumptions!$B$35 * Assumptions!D36 * Assumptions!$B$37 -> 0 | E11: =Assumptions!$B$35 * Assumptions!E36 * Assumptions!$B$37 -> 0 | F11: =Assumptions!$B$35 * Assumptions!F36 * Assumptions!$B$37 -> 0 | G11: =Assumptions!$B$35 * Assumptions!G36 * Assumptions!$B$37 -> 0 | H11: =Assumptions!$B$35 * Assumptions!H36 * Assumptions!$B$37 -> 0 | I11: =Assumptions!$B$35 * Assumptions!I36 * Assumptions!$B$37 -> 0 | L11: £ | M11: toggle × sites × £/site
A12: Accessories & consumables revenue | C12: =Assumptions!$B$38 * Assumptions!C18 * Assumptions!$B$39 -> 0 | D12: =Assumptions!$B$38 * Assumptions!D18 * Assumptions!$B$39 -> 0 | E12: =Assumptions!$B$38 * Assumptions!E18 * Assumptions!$B$39 -> 0 | F12: =Assumptions!$B$38 * Assumptions!F18 * Assumptions!$B$39 -> 0 | G12: =Assumptions!$B$38 * Assumptions!G18 * Assumptions!$B$39 -> 0 | H12: =Assumptions!$B$38 * Assumptions!H18 * Assumptions!$B$39 -> 0 | I12: =Assumptions!$B$38 * Assumptions!I18 * Assumptions!$B$39 -> 0 | L12: £ | M12: toggle × avg subs × £/sub/yr
A13: Extended warranty revenue | C13: =Assumptions!$B$41 * INDEX(Assumptions!$C$15:$K$15, 1, MAX(C5 - Scenarios!$B$26, MIN(C5, 3))) * Scenarios!$B$20 * Assumptions!$B$42 * Assumptions!$B$43 -> 0 | D13: =Assumptions!$B$41 * INDEX(Assumptions!$C$15:$K$15, 1, MAX(D5 - Scenarios!$B$26, MIN(D5, 3))) * Scenarios!$B$20 * Assumptions!$B$42 * Assumptions!$B$43 -> 0 | E13: =Assumptions!$B$41 * INDEX(Assumptions!$C$15:$K$15, 1, MAX(E5 - Scenarios!$B$26, MIN(E5, 3))) * Scenarios!$B$20 * Assumptions!$B$42 * Assumptions!$B$43 -> 0 | F13: =Assumptions!$B$41 * INDEX(Assumptions!$C$15:$K$15, 1, MAX(F5 - Scenarios!$B$26, MIN(F5, 3))) * Scenarios!$B$20 * Assumptions!$B$42 * Assumptions!$B$43 -> 0 | G13: =Assumptions!$B$41 * INDEX(Assumptions!$C$15:$K$15, 1, MAX(G5 - Scenarios!$B$26, MIN(G5, 3))) * Scenarios!$B$20 * Assumptions!$B$42 * Assumptions!$B$43 -> 0 | H13: =Assumptions!$B$41 * INDEX(Assumptions!$C$15:$K$15, 1, MAX(H5 - Scenarios!$B$26, MIN(H5, 3))) * Scenarios!$B$20 * Assumptions!$B$42 * Assumptions!$B$43 -> 0 | I13: =Assumptions!$B$41 * INDEX(Assumptions!$C$15:$K$15, 1, MAX(I5 - Scenarios!$B$26, MIN(I5, 3))) * Scenarios!$B$20 * Assumptions!$B$42 * Assumptions!$B$43 -> 0 | L13: £ | M13: toggle × delay-shifted new units × adoption × attach × £/unit
A14: TOTAL REVENUE | C14: =SUM(C9:C13) -> 0 | D14: =SUM(D9:D13) -> 0 | E14: =SUM(E9:E13) -> 53460 | F14: =SUM(F9:F13) -> 211680 | G14: =SUM(G9:G13) -> 773424 | H14: =SUM(H9:H13) -> 1723839 | I14: =SUM(I9:I13) -> 3978956.7 | L14: £
A16: 2. COST OF GOODS SOLD
A17: Hardware COGS | C17: =INDEX(Assumptions!$C$15:$K$15, 1, MAX(C5 - Scenarios!$B$26, MIN(C5, 3))) * Scenarios!$B$20 * Assumptions!C49 -> 0 | D17: =INDEX(Assumptions!$C$15:$K$15, 1, MAX(D5 - Scenarios!$B$26, MIN(D5, 3))) * Scenarios!$B$20 * Assumptions!D49 -> 0 | E17: =INDEX(Assumptions!$C$15:$K$15, 1, MAX(E5 - Scenarios!$B$26, MIN(E5, 3))) * Scenarios!$B$20 * Assumptions!E49 -> 25650 | F17: =INDEX(Assumptions!$C$15:$K$15, 1, MAX(F5 - Scenarios!$B$26, MIN(F5, 3))) * Scenarios!$B$20 * Assumptions!F49 -> 76950 | G17: =INDEX(Assumptions!$C$15:$K$15, 1, MAX(G5 - Scenarios!$B$26, MIN(G5, 3))) * Scenarios!$B$20 * Assumptions!G49 -> 259434 | H17: =INDEX(Assumptions!$C$15:$K$15, 1, MAX(H5 - Scenarios!$B$26, MIN(H5, 3))) * Scenarios!$B$20 * Assumptions!H49 -> 548796 | I17: =INDEX(Assumptions!$C$15:$K$15, 1, MAX(I5 - Scenarios!$B$26, MIN(I5, 3))) * Scenarios!$B$20 * Assumptions!I49 -> 1318050 | L17: £ | M17: delay-shifted new units × adoption × effective unit cost (BOM applied in row 49)
A18: Subscription COGS | C18: =C10 * Assumptions!$B$50 -> 0 | D18: =D10 * Assumptions!$B$50 -> 0 | E18: =E10 * Assumptions!$B$50 -> 4050 | F18: =F10 * Assumptions!$B$50 -> 19845 | G18: =G10 * Assumptions!$B$50 -> 50260.5 | H18: =H10 * Assumptions!$B$50 -> 119484.45 | I18: =I10 * Assumptions!$B$50 -> 262786.01 | L18: £ | M18: hosting / support tooling — sub rev × COGS rate
A19: Accessories COGS | C19: =C12 * (1 - Assumptions!$B$40) -> 0 | D19: =D12 * (1 - Assumptions!$B$40) -> 0 | E19: =E12 * (1 - Assumptions!$B$40) -> 0 | F19: =F12 * (1 - Assumptions!$B$40) -> 0 | G19: =G12 * (1 - Assumptions!$B$40) -> 0 | H19: =H12 * (1 - Assumptions!$B$40) -> 0 | I19: =I12 * (1 - Assumptions!$B$40) -> 0 | L19: £
A20: Extended warranty COGS | C20: =C13 * (1 - Assumptions!$B$44) -> 0 | D20: =D13 * (1 - Assumptions!$B$44) -> 0 | E20: =E13 * (1 - Assumptions!$B$44) -> 0 | F20: =F13 * (1 - Assumptions!$B$44) -> 0 | G20: =G13 * (1 - Assumptions!$B$44) -> 0 | H20: =H13 * (1 - Assumptions!$B$44) -> 0 | I20: =I13 * (1 - Assumptions!$B$44) -> 0 | L20: £
A21: TOTAL COGS | C21: =SUM(C17:C20) -> 0 | D21: =SUM(D17:D20) -> 0 | E21: =SUM(E17:E20) -> 29700 | F21: =SUM(F17:F20) -> 96795 | G21: =SUM(G17:G20) -> 309694.5 | H21: =SUM(H17:H20) -> 668280.45 | I21: =SUM(I17:I20) -> 1580836 | L21: £
A23: GROSS PROFIT | C23: =C14 - C21 -> 0 | D23: =D14 - D21 -> 0 | E23: =E14 - E21 -> 23760 | F23: =F14 - F21 -> 114885 | G23: =G14 - G21 -> 463729.5 | H23: =H14 - H21 -> 1055558.6 | I23: =I14 - I21 -> 2398120.7 | L23: £
A24: Gross margin % | C24: =IFERROR(C23/C14, 0) -> 0 | D24: =IFERROR(D23/D14, 0) -> 0 | E24: =IFERROR(E23/E14, 0) -> 0.44444444 | F24: =IFERROR(F23/F14, 0) -> 0.54272959 | G24: =IFERROR(G23/G14, 0) -> 0.59957992 | H24: =IFERROR(H23/H14, 0) -> 0.61233012 | I24: =IFERROR(I23/I14, 0) -> 0.60270088 | L24: %
A26: 3. OPERATING EXPENSES — R&D
A27: Engineering payroll (allocated) | C27: =IFERROR(Assumptions!$B$55 * Assumptions!C55 / Assumptions!C63, 0) * Assumptions!C66 -> 168952.33 | D27: =IFERROR(Assumptions!$B$55 * Assumptions!D55 / Assumptions!D63, 0) * Assumptions!D66 -> 174329.44 | E27: =IFERROR(Assumptions!$B$55 * Assumptions!E55 / Assumptions!E63, 0) * Assumptions!E66 -> 261800 | F27: =IFERROR(Assumptions!$B$55 * Assumptions!F55 / Assumptions!F63, 0) * Assumptions!F66 -> 327250 | G27: =IFERROR(Assumptions!$B$55 * Assumptions!G55 / Assumptions!G63, 0) * Assumptions!G66 -> 392700 | H27: =IFERROR(Assumptions!$B$55 * Assumptions!H55 / Assumptions!H63, 0) * Assumptions!H66 -> 458150 | I27: =IFERROR(Assumptions!$B$55 * Assumptions!I55 / Assumptions!I63, 0) * Assumptions!I66 -> 523600 | L27: £ | M27: (Eng base ÷ total base) × loaded payroll
A28: R&D non-payroll | C28: =Assumptions!C72 -> 15000 | D28: =Assumptions!D72 -> 20000 | E28: =Assumptions!E72 -> 25000 | F28: =Assumptions!F72 -> 30000 | G28: =Assumptions!G72 -> 30000 | H28: =Assumptions!H72 -> 30000 | I28: =Assumptions!I72 -> 30000 | L28: £
A29: TOTAL R&D | C29: =C27 + C28 -> 183952.33 | D29: =D27 + D28 -> 194329.44 | E29: =E27 + E28 -> 286800 | F29: =F27 + F28 -> 357250 | G29: =G27 + G28 -> 422700 | H29: =H27 + H28 -> 488150 | I29: =I27 + I28 -> 553600 | L29: £
A31: 4. OPERATING EXPENSES — REGULATORY & CLINICAL
A32: Regulatory & quality payroll (allocated) | C32: =IFERROR(Assumptions!$B$56 * Assumptions!C56 / Assumptions!C63, 0) * Assumptions!C66 -> 0 | D32: =IFERROR(Assumptions!$B$56 * Assumptions!D56 / Assumptions!D63, 0) * Assumptions!D66 -> 34337.617 | E32: =IFERROR(Assumptions!$B$56 * Assumptions!E56 / Assumptions!E63, 0) * Assumptions!E66 -> 77350 | F32: =IFERROR(Assumptions!$B$56 * Assumptions!F56 / Assumptions!F63, 0) * Assumptions!F66 -> 116025 | G32: =IFERROR(Assumptions!$B$56 * Assumptions!G56 / Assumptions!G63, 0) * Assumptions!G66 -> 154700 | H32: =IFERROR(Assumptions!$B$56 * Assumptions!H56 / Assumptions!H63, 0) * Assumptions!H66 -> 154700 | I32: =IFERROR(Assumptions!$B$56 * Assumptions!I56 / Assumptions!I63, 0) * Assumptions!I66 -> 154700 | L32: £
A33: Clinical research payroll (allocated) | C33: =IFERROR(Assumptions!$B$57 * Assumptions!C57 / Assumptions!C63, 0) * Assumptions!C66 -> 0 | D33: =IFERROR(Assumptions!$B$57 * Assumptions!D57 / Assumptions!D63, 0) * Assumptions!D66 -> 21130.841 | E33: =IFERROR(Assumptions!$B$57 * Assumptions!E57 / Assumptions!E63, 0) * Assumptions!E66 -> 47600 | F33: =IFERROR(Assumptions!$B$57 * Assumptions!F57 / Assumptions!F63, 0) * Assumptions!F66 -> 47600 | G33: =IFERROR(Assumptions!$B$57 * Assumptions!G57 / Assumptions!G63, 0) * Assumptions!G66 -> 47600 | H33: =IFERROR(Assumptions!$B$57 * Assumptions!H57 / Assumptions!H63, 0) * Assumptions!H66 -> 47600 | I33: =IFERROR(Assumptions!$B$57 * Assumptions!I57 / Assumptions!I63, 0) * Assumptions!I66 -> 47600 | L33: £
A34: One-off regulatory & clinical | C34: =Assumptions!C86 * Scenarios!$B$25 -> 0 | D34: =Assumptions!D86 * Scenarios!$B$25 -> 130000 | E34: =Assumptions!E86 * Scenarios!$B$25 -> 140000 | F34: =Assumptions!F86 * Scenarios!$B$25 -> 0 | G34: =Assumptions!G86 * Scenarios!$B$25 -> 0 | H34: =Assumptions!H86 * Scenarios!$B$25 -> 0 | I34: =Assumptions!I86 * Scenarios!$B$25 -> 0 | L34: £ | M34: QMS, NB fees, biocompat, EMC, clinical investigation × reg scenario
A35: Ongoing PMS & NB surveillance | C35: =Assumptions!C87 * Scenarios!$B$25 -> 0 | D35: =Assumptions!D87 * Scenarios!$B$25 -> 0 | E35: =Assumptions!E87 * Scenarios!$B$25 -> 0 | F35: =Assumptions!F87 * Scenarios!$B$25 -> 55000 | G35: =Assumptions!G87 * Scenarios!$B$25 -> 55000 | H35: =Assumptions!H87 * Scenarios!$B$25 -> 60000 | I35: =Assumptions!I87 * Scenarios!$B$25 -> 65000 | L35: £ | M35: Post-market obligations × reg scenario
A36: TOTAL REGULATORY & CLINICAL | C36: =SUM(C32:C35) -> 0 | D36: =SUM(D32:D35) -> 185468.46 | E36: =SUM(E32:E35) -> 264950 | F36: =SUM(F32:F35) -> 218625 | G36: =SUM(G32:G35) -> 257300 | H36: =SUM(H32:H35) -> 262300 | I36: =SUM(I32:I35) -> 267300 | L36: £
A38: 5. OPERATING EXPENSES — SALES & MARKETING
A39: Sales / BD payroll (allocated) | C39: =IFERROR(Assumptions!$B$58 * Assumptions!C58 / Assumptions!C63, 0) * Assumptions!C66 -> 0 | D39: =IFERROR(Assumptions!$B$58 * Assumptions!D58 / Assumptions!D63, 0) * Assumptions!D66 -> 0 | E39: =IFERROR(Assumptions!$B$58 * Assumptions!E58 / Assumptions!E63, 0) * Assumptions!E66 -> 57120 | F39: =IFERROR(Assumptions!$B$58 * Assumptions!F58 / Assumptions!F63, 0) * Assumptions!F66 -> 114240 | G39: =IFERROR(Assumptions!$B$58 * Assumptions!G58 / Assumptions!G63, 0) * Assumptions!G66 -> 171360 | H39: =IFERROR(Assumptions!$B$58 * Assumptions!H58 / Assumptions!H63, 0) * Assumptions!H66 -> 171360 | I39: =IFERROR(Assumptions!$B$58 * Assumptions!I58 / Assumptions!I63, 0) * Assumptions!I66 -> 171360 | L39: £
A40: Customer support payroll (allocated) | C40: =IFERROR(Assumptions!$B$60 * Assumptions!C60 / Assumptions!C63, 0) * Assumptions!C66 -> 0 | D40: =IFERROR(Assumptions!$B$60 * Assumptions!D60 / Assumptions!D63, 0) * Assumptions!D66 -> 0 | E40: =IFERROR(Assumptions!$B$60 * Assumptions!E60 / Assumptions!E63, 0) * Assumptions!E66 -> 0 | F40: =IFERROR(Assumptions!$B$60 * Assumptions!F60 / Assumptions!F63, 0) * Assumptions!F66 -> 19040 | G40: =IFERROR(Assumptions!$B$60 * Assumptions!G60 / Assumptions!G63, 0) * Assumptions!G66 -> 38080 | H40: =IFERROR(Assumptions!$B$60 * Assumptions!H60 / Assumptions!H63, 0) * Assumptions!H66 -> 57120 | I40: =IFERROR(Assumptions!$B$60 * Assumptions!I60 / Assumptions!I63, 0) * Assumptions!I66 -> 76160 | L40: £
A41: Sales commission | C41: =Assumptions!C68 -> 0 | D41: =Assumptions!D68 -> 0 | E41: =Assumptions!E68 -> 8100 | F41: =Assumptions!F68 -> 24300 | G41: =Assumptions!G68 -> 40500 | H41: =Assumptions!H68 -> 108000 | I41: =Assumptions!I68 -> 202500 | L41: £
A42: Marketing | C42: =Assumptions!C73 * Scenarios!$B$24 -> 5000 | D42: =Assumptions!D73 * Scenarios!$B$24 -> 10000 | E42: =Assumptions!E73 * Scenarios!$B$24 -> 25000 | F42: =Assumptions!F73 * Scenarios!$B$24 -> 50000 | G42: =Assumptions!G73 * Scenarios!$B$24 -> 150000 | H42: =Assumptions!H73 * Scenarios!$B$24 -> 300000 | I42: =Assumptions!I73 * Scenarios!$B$24 -> 500000 | L42: £ | M42: Marketing spend × marketing scenario
A43: TOTAL SALES & MARKETING | C43: =SUM(C39:C42) -> 5000 | D43: =SUM(D39:D42) -> 10000 | E43: =SUM(E39:E42) -> 90220 | F43: =SUM(F39:F42) -> 207580 | G43: =SUM(G39:G42) -> 399940 | H43: =SUM(H39:H42) -> 636480 | I43: =SUM(I39:I42) -> 950020 | L43: £
A45: 6. OPERATING EXPENSES — GENERAL & ADMINISTRATIVE
A46: CEO / commercial payroll (allocated) | C46: =IFERROR(Assumptions!$B$54 * Assumptions!C54 / Assumptions!C63, 0) * Assumptions!C66 -> 51197.674 | D46: =IFERROR(Assumptions!$B$54 * Assumptions!D54 / Assumptions!D63, 0) * Assumptions!D66 -> 52827.103 | E46: =IFERROR(Assumptions!$B$54 * Assumptions!E54 / Assumptions!E63, 0) * Assumptions!E66 -> 59500 | F46: =IFERROR(Assumptions!$B$54 * Assumptions!F54 / Assumptions!F63, 0) * Assumptions!F66 -> 59500 | G46: =IFERROR(Assumptions!$B$54 * Assumptions!G54 / Assumptions!G63, 0) * Assumptions!G66 -> 59500 | H46: =IFERROR(Assumptions!$B$54 * Assumptions!H54 / Assumptions!H63, 0) * Assumptions!H66 -> 59500 | I46: =IFERROR(Assumptions!$B$54 * Assumptions!I54 / Assumptions!I63, 0) * Assumptions!I66 -> 59500 | L46: £
A47: Operations / supply chain payroll (allocated) | C47: =IFERROR(Assumptions!$B$59 * Assumptions!C59 / Assumptions!C63, 0) * Assumptions!C66 -> 0 | D47: =IFERROR(Assumptions!$B$59 * Assumptions!D59 / Assumptions!D63, 0) * Assumptions!D66 -> 0 | E47: =IFERROR(Assumptions!$B$59 * Assumptions!E59 / Assumptions!E63, 0) * Assumptions!E66 -> 0 | F47: =IFERROR(Assumptions!$B$59 * Assumptions!F59 / Assumptions!F63, 0) * Assumptions!F66 -> 53550 | G47: =IFERROR(Assumptions!$B$59 * Assumptions!G59 / Assumptions!G63, 0) * Assumptions!G66 -> 53550 | H47: =IFERROR(Assumptions!$B$59 * Assumptions!H59 / Assumptions!H63, 0) * Assumptions!H66 -> 53550 | I47: =IFERROR(Assumptions!$B$59 * Assumptions!I59 / Assumptions!I63, 0) * Assumptions!I66 -> 53550 | L47: £
A48: Spare role payroll (allocated) | C48: =IFERROR(Assumptions!$B$61 * Assumptions!C61 / Assumptions!C63, 0) * Assumptions!C66 -> 0 | D48: =IFERROR(Assumptions!$B$61 * Assumptions!D61 / Assumptions!D63, 0) * Assumptions!D66 -> 0 | E48: =IFERROR(Assumptions!$B$61 * Assumptions!E61 / Assumptions!E63, 0) * Assumptions!E66 -> 0 | F48: =IFERROR(Assumptions!$B$61 * Assumptions!F61 / Assumptions!F63, 0) * Assumptions!F66 -> 0 | G48: =IFERROR(Assumptions!$B$61 * Assumptions!G61 / Assumptions!G63, 0) * Assumptions!G66 -> 0 | H48: =IFERROR(Assumptions!$B$61 * Assumptions!H61 / Assumptions!H63, 0) * Assumptions!H66 -> 0 | I48: =IFERROR(Assumptions!$B$61 * Assumptions!I61 / Assumptions!I63, 0) * Assumptions!I66 -> 0 | L48: £
A49: Travel & subsistence | C49: =Assumptions!C74 -> 8000 | D49: =Assumptions!D74 -> 12000 | E49: =Assumptions!E74 -> 25000 | F49: =Assumptions!F74 -> 40000 | G49: =Assumptions!G74 -> 55000 | H49: =Assumptions!H74 -> 70000 | I49: =Assumptions!I74 -> 85000 | L49: £
A50: Professional fees | C50: =Assumptions!C75 -> 10000 | D50: =Assumptions!D75 -> 15000 | E50: =Assumptions!E75 -> 30000 | F50: =Assumptions!F75 -> 40000 | G50: =Assumptions!G75 -> 50000 | H50: =Assumptions!H75 -> 60000 | I50: =Assumptions!I75 -> 70000 | L50: £
A51: IT and software | C51: =Assumptions!C76 -> 6000 | D51: =Assumptions!D76 -> 10000 | E51: =Assumptions!E76 -> 20000 | F51: =Assumptions!F76 -> 35000 | G51: =Assumptions!G76 -> 55000 | H51: =Assumptions!H76 -> 75000 | I51: =Assumptions!I76 -> 95000 | L51: £
A52: Facilities | C52: =Assumptions!C80 -> 0 | D52: =Assumptions!D80 -> 20000 | E52: =Assumptions!E80 -> 24000 | F52: =Assumptions!F80 -> 35000 | G52: =Assumptions!G80 -> 45000 | H52: =Assumptions!H80 -> 55000 | I52: =Assumptions!I80 -> 65000 | L52: £
A53: Insurance | C53: =Assumptions!C83 -> 6000 | D53: =Assumptions!D83 -> 12000 | E53: =Assumptions!E83 -> 20000 | F53: =Assumptions!F83 -> 28000 | G53: =Assumptions!G83 -> 36000 | H53: =Assumptions!H83 -> 44000 | I53: =Assumptions!I83 -> 50000 | L53: £
A54: TOTAL G&A | C54: =SUM(C46:C53) -> 81197.674 | D54: =SUM(D46:D53) -> 121827.1 | E54: =SUM(E46:E53) -> 178500 | F54: =SUM(F46:F53) -> 291050 | G54: =SUM(G46:G53) -> 354050 | H54: =SUM(H46:H53) -> 417050 | I54: =SUM(I46:I53) -> 478050 | L54: £
A56: TOTAL OPERATING EXPENSES | C56: =C29 + C36 + C43 + C54 -> 270150 | D56: =D29 + D36 + D43 + D54 -> 511625 | E56: =E29 + E36 + E43 + E54 -> 820470 | F56: =F29 + F36 + F43 + F54 -> 1074505 | G56: =G29 + G36 + G43 + G54 -> 1433990 | H56: =H29 + H36 + H43 + H54 -> 1803980 | I56: =I29 + I36 + I43 + I54 -> 2248970 | L56: £
A58: EBITDA | C58: =C23 - C56 -> -270150 | D58: =D23 - D56 -> -511625 | E58: =E23 - E56 -> -796710 | F58: =F23 - F56 -> -959620 | G58: =G23 - G56 -> -970260.5 | H58: =H23 - H56 -> -748421.45 | I58: =I23 - I56 -> 149150.7 | L58: £
A59: EBITDA margin % | C59: =IFERROR(C58/C14, 0) -> 0 | D59: =IFERROR(D58/D14, 0) -> 0 | E59: =IFERROR(E58/E14, 0) -> -14.902918 | F59: =IFERROR(F58/F14, 0) -> -4.5333522 | G59: =IFERROR(G58/G14, 0) -> -1.2545001 | H59: =IFERROR(H58/H14, 0) -> -0.43415972 | I59: =IFERROR(I58/I14, 0) -> 0.037484875 | L59: %
A61: Depreciation & amortisation | C61: =Assumptions!C105 -> 1300 | D61: =Assumptions!D105 -> 2500 | E61: =Assumptions!E105 -> 5500 | F61: =Assumptions!F105 -> 9500 | G61: =Assumptions!G105 -> 15500 | H61: =Assumptions!H105 -> 16600 | I61: =Assumptions!I105 -> 18542.857 | L61: £
A63: EBIT (Operating profit / loss) | C63: =C58 - C61 -> -271450 | D63: =D58 - D61 -> -514125 | E63: =E58 - E61 -> -802210 | F63: =F58 - F61 -> -969120 | G63: =G58 - G61 -> -985760.5 | H63: =H58 - H61 -> -765021.45 | I63: =I58 - I61 -> 130607.84 | L63: £
A64: + Interest income on opening cash | C64: ='Cash flow'!C38 * Assumptions!$B$124 -> 0 | D64: ='Cash flow'!D38 * Assumptions!$B$124 -> 22534.784 | E64: ='Cash flow'!E38 * Assumptions!$B$124 -> 9514.1018 | F64: ='Cash flow'!F38 * Assumptions!$B$124 -> 40037.088 | G64: ='Cash flow'!G38 * Assumptions!$B$124 -> 14294.941 | H64: ='Cash flow'!H38 * Assumptions!$B$124 -> 31164.892 | I64: ='Cash flow'!I38 * Assumptions!$B$124 -> 14742.733 | L64: £ | M64: Cash flow opening cash × Assumptions!$B$124
A65: 7. TAX (with loss carry-forward and R&D credit)
A66: Cumulative losses brought forward | C66: =OFFSET(C66, 7, -1) -> 0 | D66: =OFFSET(D66, 7, -1) -> 271450 | E66: =OFFSET(E66, 7, -1) -> 763040.22 | F66: =OFFSET(F66, 7, -1) -> 1555736.1 | G66: =OFFSET(G66, 7, -1) -> 2484819 | H66: =OFFSET(H66, 7, -1) -> 3456284.6 | I66: =OFFSET(I66, 7, -1) -> 4190141.1 | L66: £ | M66: Carries unused trading losses indefinitely
A67: Losses utilised this year | C67: =MIN(C66, MAX(0, C63 + C64)) -> 0 | D67: =MIN(D66, MAX(0, D63 + D64)) -> 0 | E67: =MIN(E66, MAX(0, E63 + E64)) -> 0 | F67: =MIN(F66, MAX(0, F63 + F64)) -> 0 | G67: =MIN(G66, MAX(0, G63 + G64)) -> 0 | H67: =MIN(H66, MAX(0, H63 + H64)) -> 0 | I67: =MIN(I66, MAX(0, I63 + I64)) -> 145350.57 | L67: £ | M67: MIN(losses BF, max(0, EBIT + interest))
A68: Taxable profit | C68: =MAX(0, C63 + C64 - C67) -> 0 | D68: =MAX(0, D63 + D64 - D67) -> 0 | E68: =MAX(0, E63 + E64 - E67) -> 0 | F68: =MAX(0, F63 + F64 - F67) -> 0 | G68: =MAX(0, G63 + G64 - G67) -> 0 | H68: =MAX(0, H63 + H64 - H67) -> 0 | I68: =MAX(0, I63 + I64 - I67) -> 0 | L68: £ | M68: MAX(0, EBIT + interest − losses utilised)
A69: Corporation tax | C69: =C68 * Assumptions!$B$116 -> 0 | D69: =D68 * Assumptions!$B$116 -> 0 | E69: =E68 * Assumptions!$B$116 -> 0 | F69: =F68 * Assumptions!$B$116 -> 0 | G69: =G68 * Assumptions!$B$116 -> 0 | H69: =H68 * Assumptions!$B$116 -> 0 | I69: =I68 * Assumptions!$B$116 -> 0 | L69: £ | M69: taxable profit × 25%
A70: Qualifying R&D spend | C70: =C27*Assumptions!$B$119 + C32*Assumptions!$B$120 + C33*Assumptions!$B$121 + C28*Assumptions!$B$123 + C34*Assumptions!$B$122 -> 116371.4 | D70: =D27*Assumptions!$B$119 + D32*Assumptions!$B$120 + D33*Assumptions!$B$121 + D28*Assumptions!$B$123 + D34*Assumptions!$B$122 -> 209671.96 | E70: =E27*Assumptions!$B$119 + E32*Assumptions!$B$120 + E33*Assumptions!$B$121 + E28*Assumptions!$B$123 + E34*Assumptions!$B$122 -> 297300 | F70: =F27*Assumptions!$B$119 + F32*Assumptions!$B$120 + F33*Assumptions!$B$121 + F28*Assumptions!$B$123 + F34*Assumptions!$B$122 -> 287040 | G70: =G27*Assumptions!$B$119 + G32*Assumptions!$B$120 + G33*Assumptions!$B$121 + G28*Assumptions!$B$123 + G34*Assumptions!$B$122 -> 341780 | H70: =H27*Assumptions!$B$119 + H32*Assumptions!$B$120 + H33*Assumptions!$B$121 + H28*Assumptions!$B$123 + H34*Assumptions!$B$122 -> 381050 | I70: =I27*Assumptions!$B$119 + I32*Assumptions!$B$120 + I33*Assumptions!$B$121 + I28*Assumptions!$B$123 + I34*Assumptions!$B$122 -> 420320 | L70: £ | M70: Eng×60% + Reg×40% + Clin×30% + R&D npp×100% + clin inv×50%
A71: R&D tax credit | C71: =-C70 * Assumptions!$B$118 * Assumptions!$B$117 -> -21645.08 | D71: =-D70 * Assumptions!$B$118 * Assumptions!$B$117 -> -38998.985 | E71: =-E70 * Assumptions!$B$118 * Assumptions!$B$117 -> -55297.8 | F71: =-F70 * Assumptions!$B$118 * Assumptions!$B$117 -> -53389.44 | G71: =-G70 * Assumptions!$B$118 * Assumptions!$B$117 -> -63571.08 | H71: =-H70 * Assumptions!$B$118 * Assumptions!$B$117 -> -70875.3 | I71: =-I70 * Assumptions!$B$118 * Assumptions!$B$117 -> -78179.52 | L71: £ | M71: −qualifying × effective rate × on/off; cash-back when loss-making
A72: Net tax expense / (credit) | C72: =C69 + C71 -> -21645.08 | D72: =D69 + D71 -> -38998.985 | E72: =E69 + E71 -> -55297.8 | F72: =F69 + F71 -> -53389.44 | G72: =G69 + G71 -> -63571.08 | H72: =H69 + H71 -> -70875.3 | I72: =I69 + I71 -> -78179.52 | L72: £
A73: Cumulative losses carried forward | C73: =C66 + MAX(0, -(C63 + C64)) - C67 -> 271450 | D73: =D66 + MAX(0, -(D63 + D64)) - D67 -> 763040.22 | E73: =E66 + MAX(0, -(E63 + E64)) - E67 -> 1555736.1 | F73: =F66 + MAX(0, -(F63 + F64)) - F67 -> 2484819 | G73: =G66 + MAX(0, -(G63 + G64)) - G67 -> 3456284.6 | H73: =H66 + MAX(0, -(H63 + H64)) - H67 -> 4190141.1 | I73: =I66 + MAX(0, -(I63 + I64)) - I67 -> 4044790.6 | L73: £ | M73: prior CF + this year's loss − losses utilised
A75: NET INCOME | C75: =C63 + C64 - C72 -> -249804.92 | D75: =D63 + D64 - D72 -> -452591.23 | E75: =E63 + E64 - E72 -> -737398.1 | F75: =F63 + F64 - F72 -> -875693.47 | G75: =G63 + G64 - G72 -> -907894.48 | H75: =H63 + H64 - H72 -> -662981.26 | I75: =I63 + I64 - I72 -> 223530.09 | L75: £
A76: Net margin % | C76: =IFERROR(C75/C14, 0) -> 0 | D76: =IFERROR(D75/D14, 0) -> 0 | E76: =IFERROR(E75/E14, 0) -> -13.793455 | F76: =IFERROR(F75/F14, 0) -> -4.1368739 | G76: =IFERROR(G75/G14, 0) -> -1.1738639 | H76: =IFERROR(H75/H14, 0) -> -0.38459581 | I76: =IFERROR(I75/I14, 0) -> 0.056178066 | L76: %

Sheet Cash flow
A1: Cash Flow — 7-year projection (indirect method)
A2: Builds operating cash from EBIT, layers in working capital and capex, then adds equity injections to derive closing cash. The minimum closing-cash point is the binding funding requirement.
A4: Year | C4: =Assumptions!C4 -> Y1 | D4: =Assumptions!D4 -> Y2 | E4: =Assumptions!E4 -> Y3 | F4: =Assumptions!F4 -> Y4 | G4: =Assumptions!G4 -> Y5 | H4: =Assumptions!H4 -> Y6 | I4: =Assumptions!I4 -> Y7
A5: Period number | C5: =Assumptions!C5 -> 1 | D5: =Assumptions!D5 -> 2 | E5: =Assumptions!E5 -> 3 | F5: =Assumptions!F5 -> 4 | G5: =Assumptions!G5 -> 5 | H5: =Assumptions!H5 -> 6 | I5: =Assumptions!I5 -> 7
A6: Phase | C6: =Assumptions!C7 -> 1 | D6: =Assumptions!D7 -> 1 | E6: =Assumptions!E7 -> 2 | F6: =Assumptions!F7 -> 2 | G6: =Assumptions!G7 -> 3 | H6: =Assumptions!H7 -> 3 | I6: =Assumptions!I7 -> 3
A8: 1. OPERATING CASH FLOW
A9: EBIT (operating profit / loss) | C9: ='P&L'!C63 -> -271450 | D9: ='P&L'!D63 -> -514125 | E9: ='P&L'!E63 -> -802210 | F9: ='P&L'!F63 -> -969120 | G9: ='P&L'!G63 -> -985760.5 | H9: ='P&L'!H63 -> -765021.45 | I9: ='P&L'!I63 -> 130607.84 | L9: £
A10: + Depreciation & amortisation (non-cash) | C10: ='P&L'!C61 -> 1300 | D10: ='P&L'!D61 -> 2500 | E10: ='P&L'!E61 -> 5500 | F10: ='P&L'!F61 -> 9500 | G10: ='P&L'!G61 -> 15500 | H10: ='P&L'!H61 -> 16600 | I10: ='P&L'!I61 -> 18542.857 | L10: £
A11: = EBITDA equivalent | C11: =C9 + C10 -> -270150 | D11: =D9 + D10 -> -511625 | E11: =E9 + E10 -> -796710 | F11: =F9 + F10 -> -959620 | G11: =G9 + G10 -> -970260.5 | H11: =H9 + H10 -> -748421.45 | I11: =I9 + I10 -> 149150.7 | L11: £
A12: − Tax paid / + R&D credit received | C12: =-'P&L'!C72 -> 21645.08 | D12: =-'P&L'!D72 -> 38998.985 | E12: =-'P&L'!E72 -> 55297.8 | F12: =-'P&L'!F72 -> 53389.44 | G12: =-'P&L'!G72 -> 63571.08 | H12: =-'P&L'!H72 -> 70875.3 | I12: =-'P&L'!I72 -> 78179.52 | L12: £ | M12: Assumes credit received in year incurred (1-yr lag in reality)
A13: = Operating cash before working capital | C13: =C11 + C12 -> -248504.92 | D13: =D11 + D12 -> -472626.01 | E13: =E11 + E12 -> -741412.2 | F13: =F11 + F12 -> -906230.56 | G13: =G11 + G12 -> -906689.42 | H13: =H11 + H12 -> -677546.15 | I13: =I11 + I12 -> 227330.21 | L13: £
A15: 2. WORKING CAPITAL CHANGES (positive = cash inflow)
A16: Inventory (end of year) | C16: =Assumptions!$B$110 * 'P&L'!C21 / 365 -> 0 | D16: =Assumptions!$B$110 * 'P&L'!D21 / 365 -> 0 | E16: =Assumptions!$B$110 * 'P&L'!E21 / 365 -> 6102.7397 | F16: =Assumptions!$B$110 * 'P&L'!F21 / 365 -> 19889.384 | G16: =Assumptions!$B$110 * 'P&L'!G21 / 365 -> 63635.856 | H16: =Assumptions!$B$110 * 'P&L'!H21 / 365 -> 137317.9 | I16: =Assumptions!$B$110 * 'P&L'!I21 / 365 -> 324829.32 | L16: £ | M16: DIO × COGS / 365
A17: (Increase) / decrease in inventory | C17: =-(C16 - OFFSET(C16, 0, -1)) -> 0 | D17: =-(D16 - OFFSET(D16, 0, -1)) -> 0 | E17: =-(E16 - OFFSET(E16, 0, -1)) -> -6102.7397 | F17: =-(F16 - OFFSET(F16, 0, -1)) -> -13786.644 | G17: =-(G16 - OFFSET(G16, 0, -1)) -> -43746.473 | H17: =-(H16 - OFFSET(H16, 0, -1)) -> -73682.045 | I17: =-(I16 - OFFSET(I16, 0, -1)) -> -187511.42 | L17: £
A18: Receivables (end of year) | C18: =Assumptions!$B$111 * 'P&L'!C14 / 365 -> 0 | D18: =Assumptions!$B$111 * 'P&L'!D14 / 365 -> 0 | E18: =Assumptions!$B$111 * 'P&L'!E14 / 365 -> 6590.9589 | F18: =Assumptions!$B$111 * 'P&L'!F14 / 365 -> 26097.534 | G18: =Assumptions!$B$111 * 'P&L'!G14 / 365 -> 95353.644 | H18: =Assumptions!$B$111 * 'P&L'!H14 / 365 -> 212528.1 | I18: =Assumptions!$B$111 * 'P&L'!I14 / 365 -> 490556.31 | L18: £ | M18: DSO × revenue / 365
A19: (Increase) / decrease in receivables | C19: =-(C18 - OFFSET(C18, 0, -1)) -> 0 | D19: =-(D18 - OFFSET(D18, 0, -1)) -> 0 | E19: =-(E18 - OFFSET(E18, 0, -1)) -> -6590.9589 | F19: =-(F18 - OFFSET(F18, 0, -1)) -> -19506.575 | G19: =-(G18 - OFFSET(G18, 0, -1)) -> -69256.11 | H19: =-(H18 - OFFSET(H18, 0, -1)) -> -117174.45 | I19: =-(I18 - OFFSET(I18, 0, -1)) -> -278028.21 | L19: £
A20: Payables (end of year) | C20: =Assumptions!$B$112 * ('P&L'!C21 + ('P&L'!C56 - Assumptions!C69)) / 365 -> 6164.3836 | D20: =Assumptions!$B$112 * ('P&L'!D21 + ('P&L'!D56 - Assumptions!D69)) / 365 -> 28232.877 | E20: =Assumptions!$B$112 * ('P&L'!E21 + ('P&L'!E56 - Assumptions!E69)) / 365 -> 41757.534 | F20: =Assumptions!$B$112 * ('P&L'!F21 + ('P&L'!F56 - Assumptions!F69)) / 365 -> 50522.671 | G20: =Assumptions!$B$112 * ('P&L'!G21 + ('P&L'!G56 - Assumptions!G69)) / 365 -> 96866.445 | H20: =Assumptions!$B$112 * ('P&L'!H21 + ('P&L'!H56 - Assumptions!H69)) / 365 -> 167952.38 | I20: =Assumptions!$B$112 * ('P&L'!I21 + ('P&L'!I56 - Assumptions!I69)) / 365 -> 313253.75 | L20: £ | M20: DPO × (COGS + non-payroll opex) / 365
A21: Increase / (decrease) in payables | C21: =C20 - OFFSET(C20, 0, -1) -> 6164.3836 | D21: =D20 - OFFSET(D20, 0, -1) -> 22068.493 | E21: =E20 - OFFSET(E20, 0, -1) -> 13524.658 | F21: =F20 - OFFSET(F20, 0, -1) -> 8765.137 | G21: =G20 - OFFSET(G20, 0, -1) -> 46343.774 | H21: =H20 - OFFSET(H20, 0, -1) -> 71085.939 | I21: =I20 - OFFSET(I20, 0, -1) -> 145301.37 | L21: £
A22: Deferred revenue (end of year) | C22: ='P&L'!C10 * 0.5 -> 0 | D22: ='P&L'!D10 * 0.5 -> 0 | E22: ='P&L'!E10 * 0.5 -> 13500 | F22: ='P&L'!F10 * 0.5 -> 66150 | G22: ='P&L'!G10 * 0.5 -> 167535 | H22: ='P&L'!H10 * 0.5 -> 398281.5 | I22: ='P&L'!I10 * 0.5 -> 875953.35 | L22: £ | M22: ≈ subscription revenue × 0.5 (annual prepay convention)
A23: Increase / (decrease) in deferred revenue | C23: =C22 - OFFSET(C22, 0, -1) -> 0 | D23: =D22 - OFFSET(D22, 0, -1) -> 0 | E23: =E22 - OFFSET(E22, 0, -1) -> 13500 | F23: =F22 - OFFSET(F22, 0, -1) -> 52650 | G23: =G22 - OFFSET(G22, 0, -1) -> 101385 | H23: =H22 - OFFSET(H22, 0, -1) -> 230746.5 | I23: =I22 - OFFSET(I22, 0, -1) -> 477671.85 | L23: £
A24: Total working capital change | C24: =C17 + C19 + C21 + C23 -> 6164.3836 | D24: =D17 + D19 + D21 + D23 -> 22068.493 | E24: =E17 + E19 + E21 + E23 -> 14330.959 | F24: =F17 + F19 + F21 + F23 -> 28121.918 | G24: =G17 + G19 + G21 + G23 -> 34726.192 | H24: =H17 + H19 + H21 + H23 -> 110975.94 | I24: =I17 + I19 + I21 + I23 -> 157433.59 | L24: £
A25: + Interest income on opening cash | C25: ='P&L'!C64 -> 0 | D25: ='P&L'!D64 -> 22534.784 | E25: ='P&L'!E64 -> 9514.1018 | F25: ='P&L'!F64 -> 40037.088 | G25: ='P&L'!G64 -> 14294.941 | H25: ='P&L'!H64 -> 31164.892 | I25: ='P&L'!I64 -> 14742.733 | L25: £ | M25: Mirrors P&L line; cash-effective in same year
A26: NET CASH FROM OPERATIONS | C26: =C13 + C24 + C25 -> -242340.54 | D26: =D13 + D24 + D25 -> -428022.74 | E26: =E13 + E24 + E25 -> -717567.14 | F26: =F13 + F24 + F25 -> -838071.55 | G26: =G13 + G24 + G25 -> -857668.29 | H26: =H13 + H24 + H25 -> -535405.32 | I26: =I13 + I24 + I25 -> 399506.54 | L26: £
A28: 3. INVESTING CASH FLOW
A29: Capex (cash outflow) | C29: =-Assumptions!C103 -> -6500 | D29: =-Assumptions!D103 -> -6000 | E29: =-Assumptions!E103 -> -15000 | F29: =-Assumptions!F103 -> -20000 | G29: =-Assumptions!G103 -> -30000 | H29: =-Assumptions!H103 -> -12000 | I29: =-Assumptions!I103 -> -22000 | L29: £ | M29: Linked from Assumptions capex schedule
A30: NET CASH FROM INVESTING | C30: =C29 -> -6500 | D30: =D29 -> -6000 | E30: =E29 -> -15000 | F30: =F29 -> -20000 | G30: =G29 -> -30000 | H30: =H29 -> -12000 | I30: =I29 -> -22000 | L30: £
A32: 4. FINANCING CASH FLOW
A33: Equity injections | C33: =Assumptions!C126 -> 1000000 | D33: =Assumptions!D126 -> 0 | E33: =Assumptions!E126 -> 1750000 | F33: =Assumptions!F126 -> 0 | G33: =Assumptions!G126 -> 1450000 | H33: =Assumptions!H126 -> 0 | I33: =Assumptions!I126 -> 0 | L33: £ | M33: Mechanical plug — sized to keep closing cash ≥ buffer
A34: NET CASH FROM FINANCING | C34: =C33 -> 1000000 | D34: =D33 -> 0 | E34: =E33 -> 1750000 | F34: =F33 -> 0 | G34: =G33 -> 1450000 | H34: =H33 -> 0 | I34: =I33 -> 0 | L34: £
A36: 5. CASH POSITION
A37: Net change in cash | C37: =C26 + C30 + C34 -> 751159.46 | D37: =D26 + D30 + D34 -> -434022.74 | E37: =E26 + E30 + E34 -> 1017432.9 | F37: =F26 + F30 + F34 -> -858071.55 | G37: =G26 + G30 + G34 -> 562331.71 | H37: =H26 + H30 + H34 -> -547405.32 | I37: =I26 + I30 + I34 -> 377506.54 | L37: £
A38: Opening cash | C38: =OFFSET(C38, 1, -1) -> 0 | D38: =OFFSET(D38, 1, -1) -> 751159.46 | E38: =OFFSET(E38, 1, -1) -> 317136.73 | F38: =OFFSET(F38, 1, -1) -> 1334569.6 | G38: =OFFSET(G38, 1, -1) -> 476498.03 | H38: =OFFSET(H38, 1, -1) -> 1038829.7 | I38: =OFFSET(I38, 1, -1) -> 491424.43 | L38: £
A39: Closing cash | C39: =C38 + C37 -> 751159.46 | D39: =D38 + D37 -> 317136.73 | E39: =E38 + E37 -> 1334569.6 | F39: =F38 + F37 -> 476498.03 | G39: =G38 + G37 -> 1038829.7 | H39: =H38 + H37 -> 491424.43 | I39: =I38 + I37 -> 868930.97 | L39: £
A40: Minimum cash buffer (target floor) | C40: =Assumptions!$B$127 -> 100000 | D40: =Assumptions!$B$127 -> 100000 | E40: =Assumptions!$B$127 -> 100000 | F40: =Assumptions!$B$127 -> 100000 | G40: =Assumptions!$B$127 -> 100000 | H40: =Assumptions!$B$127 -> 100000 | I40: =Assumptions!$B$127 -> 100000 | L40: £
A41: Buffer breached? (1 = closing cash below buffer) | C41: =IF(C39 < C40, 1, 0) -> 0 | D41: =IF(D39 < D40, 1, 0) -> 0 | E41: =IF(E39 < E40, 1, 0) -> 0 | F41: =IF(F39 < F40, 1, 0) -> 0 | G41: =IF(G39 < G40, 1, 0) -> 0 | H41: =IF(H39 < H40, 1, 0) -> 0 | I41: =IF(I39 < I40, 1, 0) -> 0 | L41: flag
A42: Cumulative ops + investing (excludes financing) | C42: =C26 + C30 + OFFSET(C42, 0, -1) -> -248840.54 | D42: =D26 + D30 + OFFSET(D42, 0, -1) -> -682863.27 | E42: =E26 + E30 + OFFSET(E42, 0, -1) -> -1415430.4 | F42: =F26 + F30 + OFFSET(F42, 0, -1) -> -2273502 | G42: =G26 + G30 + OFFSET(G42, 0, -1) -> -3161170.3 | H42: =H26 + H30 + OFFSET(H42, 0, -1) -> -3708575.6 | I42: =I26 + I30 + OFFSET(I42, 0, -1) -> -3331069 | L42: £ | M42: Running unfunded cash position; lowest point sets the funding floor
A44: 6. CASH FLOW SUMMARY
A45: Minimum closing-cash point over horizon | B45: =MIN(C39:I39) -> 317136.73 | L45: £ | M45: With the equity plug — must stay above the buffer
A46: Year of minimum closing cash | B46: =INDEX($C$4:$K$4, MATCH(MIN(C39:I39), C39:I39, 0)) -> Y2
A47: Peak unfunded cash trough | B47: =MIN(C42:K42) -> -3708575.6 | L47: £ | M47: Most-negative cumulative ops+investing — the gross funding need
A48: Year of peak unfunded trough | B48: =INDEX($C$4:$K$4, MATCH(MIN(C42:K42), C42:K42, 0)) -> Y6
A49: Total equity raised through horizon | B49: =SUM(C33:K33) -> 4200000 | L49: £
A50: Cumulative net cash from operations through Y7 | B50: =SUM(C26:K26) -> -3219569 | L50: £
A51: Total capex through horizon | B51: =-SUM(C29:K29) -> 111500 | L51: £
A52: First year of positive operating cash flow | B52: =IFERROR(INDEX($C$4:$K$4, MATCH(TRUE(), C26:K26>0, 0)), "—") -> Y7
A53: First year of self-funded positive cash (ops + investing) | B53: =IFERROR(INDEX($C$4:$K$4, MATCH(TRUE(), (C26:K26+C30:K30)>0, 0)), "—") -> Y7

Sheet Balance sheet
A1: Balance Sheet — 7-year projection (year-end)
A2: Aggregates working-capital and PP&E balances from the Cash flow / Assumptions tabs, plus cumulative share capital and retained earnings. Balance check row must be £0 every year.
A4: Year | C4: =Assumptions!C4 -> Y1 | D4: =Assumptions!D4 -> Y2 | E4: =Assumptions!E4 -> Y3 | F4: =Assumptions!F4 -> Y4 | G4: =Assumptions!G4 -> Y5 | H4: =Assumptions!H4 -> Y6 | I4: =Assumptions!I4 -> Y7
A5: Period number | C5: =Assumptions!C5 -> 1 | D5: =Assumptions!D5 -> 2 | E5: =Assumptions!E5 -> 3 | F5: =Assumptions!F5 -> 4 | G5: =Assumptions!G5 -> 5 | H5: =Assumptions!H5 -> 6 | I5: =Assumptions!I5 -> 7
A6: Phase | C6: =Assumptions!C7 -> 1 | D6: =Assumptions!D7 -> 1 | E6: =Assumptions!E7 -> 2 | F6: =Assumptions!F7 -> 2 | G6: =Assumptions!G7 -> 3 | H6: =Assumptions!H7 -> 3 | I6: =Assumptions!I7 -> 3
A8: 1. ASSETS
A9: Cash and cash equivalents | C9: ='Cash flow'!C39 -> 751159.46 | D9: ='Cash flow'!D39 -> 317136.73 | E9: ='Cash flow'!E39 -> 1334569.6 | F9: ='Cash flow'!F39 -> 476498.03 | G9: ='Cash flow'!G39 -> 1038829.7 | H9: ='Cash flow'!H39 -> 491424.43 | I9: ='Cash flow'!I39 -> 868930.97 | L9: £
A10: Accounts receivable | C10: ='Cash flow'!C18 -> 0 | D10: ='Cash flow'!D18 -> 0 | E10: ='Cash flow'!E18 -> 6590.9589 | F10: ='Cash flow'!F18 -> 26097.534 | G10: ='Cash flow'!G18 -> 95353.644 | H10: ='Cash flow'!H18 -> 212528.1 | I10: ='Cash flow'!I18 -> 490556.31 | L10: £
A11: Inventory | C11: ='Cash flow'!C16 -> 0 | D11: ='Cash flow'!D16 -> 0 | E11: ='Cash flow'!E16 -> 6102.7397 | F11: ='Cash flow'!F16 -> 19889.384 | G11: ='Cash flow'!G16 -> 63635.856 | H11: ='Cash flow'!H16 -> 137317.9 | I11: ='Cash flow'!I16 -> 324829.32 | L11: £
A12: Total current assets | C12: =SUM(C9:C11) -> 751159.46 | D12: =SUM(D9:D11) -> 317136.73 | E12: =SUM(E9:E11) -> 1347263.3 | F12: =SUM(F9:F11) -> 522484.95 | G12: =SUM(G9:G11) -> 1197819.2 | H12: =SUM(H9:H11) -> 841270.43 | I12: =SUM(I9:I11) -> 1684316.6 | L12: £
A14: PP&E (gross — cumulative capex) | C14: =Assumptions!C104 -> 6500 | D14: =Assumptions!D104 -> 12500 | E14: =Assumptions!E104 -> 27500 | F14: =Assumptions!F104 -> 47500 | G14: =Assumptions!G104 -> 77500 | H14: =Assumptions!H104 -> 89500 | I14: =Assumptions!I104 -> 111500 | L14: £
A15: Less: accumulated depreciation | C15: =-Assumptions!C106 -> -1300 | D15: =-Assumptions!D106 -> -3800 | E15: =-Assumptions!E106 -> -9300 | F15: =-Assumptions!F106 -> -18800 | G15: =-Assumptions!G106 -> -34300 | H15: =-Assumptions!H106 -> -50900 | I15: =-Assumptions!I106 -> -69442.857 | L15: £
A16: Net PP&E | C16: =C14 + C15 -> 5200 | D16: =D14 + D15 -> 8700 | E16: =E14 + E15 -> 18200 | F16: =F14 + F15 -> 28700 | G16: =G14 + G15 -> 43200 | H16: =H14 + H15 -> 38600 | I16: =I14 + I15 -> 42057.143 | L16: £
A18: TOTAL ASSETS | C18: =C12 + C16 -> 756359.46 | D18: =D12 + D16 -> 325836.73 | E18: =E12 + E16 -> 1365463.3 | F18: =F12 + F16 -> 551184.95 | G18: =G12 + G16 -> 1241019.2 | H18: =H12 + H16 -> 879870.43 | I18: =I12 + I16 -> 1726373.7 | L18: £
A20: 2. LIABILITIES
A21: Accounts payable | C21: ='Cash flow'!C20 -> 6164.3836 | D21: ='Cash flow'!D20 -> 28232.877 | E21: ='Cash flow'!E20 -> 41757.534 | F21: ='Cash flow'!F20 -> 50522.671 | G21: ='Cash flow'!G20 -> 96866.445 | H21: ='Cash flow'!H20 -> 167952.38 | I21: ='Cash flow'!I20 -> 313253.75 | L21: £
A22: Deferred revenue (annual prepay) | C22: ='Cash flow'!C22 -> 0 | D22: ='Cash flow'!D22 -> 0 | E22: ='Cash flow'!E22 -> 13500 | F22: ='Cash flow'!F22 -> 66150 | G22: ='Cash flow'!G22 -> 167535 | H22: ='Cash flow'!H22 -> 398281.5 | I22: ='Cash flow'!I22 -> 875953.35 | L22: £
A23: Total current liabilities | C23: =C21 + C22 -> 6164.3836 | D23: =D21 + D22 -> 28232.877 | E23: =E21 + E22 -> 55257.534 | F23: =F21 + F22 -> 116672.67 | G23: =G21 + G22 -> 264401.45 | H23: =H21 + H22 -> 566233.88 | I23: =I21 + I22 -> 1189207.1 | L23: £
A25: TOTAL LIABILITIES | C25: =C23 -> 6164.3836 | D25: =D23 -> 28232.877 | E25: =E23 -> 55257.534 | F25: =F23 -> 116672.67 | G25: =G23 -> 264401.45 | H25: =H23 -> 566233.88 | I25: =I23 -> 1189207.1 | L25: £
A27: 3. EQUITY
A28: Share capital (cumulative equity raised) | C28: =SUM(Assumptions!$C$126:C126) -> 1000000 | D28: =SUM(Assumptions!$C$126:D126) -> 1000000 | E28: =SUM(Assumptions!$C$126:E126) -> 2750000 | F28: =SUM(Assumptions!$C$126:F126) -> 2750000 | G28: =SUM(Assumptions!$C$126:G126) -> 4200000 | H28: =SUM(Assumptions!$C$126:H126) -> 4200000 | I28: =SUM(Assumptions!$C$126:I126) -> 4200000 | L28: £ | M28: Running sum of equity injections
A29: Retained earnings (cumulative NI) | C29: =SUM('P&L'!$C$75:C75) -> -249804.92 | D29: =SUM('P&L'!$C$75:D75) -> -702396.15 | E29: =SUM('P&L'!$C$75:E75) -> -1439794.2 | F29: =SUM('P&L'!$C$75:F75) -> -2315487.7 | G29: =SUM('P&L'!$C$75:G75) -> -3223382.2 | H29: =SUM('P&L'!$C$75:H75) -> -3886363.5 | I29: =SUM('P&L'!$C$75:I75) -> -3662833.4 | L29: £ | M29: Running sum of P&L net income
A30: TOTAL EQUITY | C30: =C28 + C29 -> 750195.08 | D30: =D28 + D29 -> 297603.85 | E30: =E28 + E29 -> 1310205.8 | F30: =F28 + F29 -> 434512.28 | G30: =G28 + G29 -> 976617.8 | H30: =H28 + H29 -> 313636.54 | I30: =I28 + I29 -> 537166.63 | L30: £
A32: 4. BALANCE CHECK
A33: Total liabilities + equity | C33: =C25 + C30 -> 756359.46 | D33: =D25 + D30 -> 325836.73 | E33: =E25 + E30 -> 1365463.3 | F33: =F25 + F30 -> 551184.95 | G33: =G25 + G30 -> 1241019.2 | H33: =H25 + H30 -> 879870.43 | I33: =I25 + I30 -> 1726373.7 | L33: £
A34: Difference (assets − L − E; should be 0) | C34: =C18 - C33 -> 0 | D34: =D18 - D33 -> 0 | E34: =E18 - E33 -> 0 | F34: =F18 - F33 -> 0 | G34: =G18 - G33 -> 0 | H34: =H18 - H33 -> 0 | I34: =I18 - I33 -> 0 | L34: £
A35: BS balanced? (1 = yes within £1 tolerance) | C35: =IF(ABS(C34) < 1, 1, 0) -> 1 | D35: =IF(ABS(D34) < 1, 1, 0) -> 1 | E35: =IF(ABS(E34) < 1, 1, 0) -> 1 | F35: =IF(ABS(F34) < 1, 1, 0) -> 1 | G35: =IF(ABS(G34) < 1, 1, 0) -> 1 | H35: =IF(ABS(H34) < 1, 1, 0) -> 1 | I35: =IF(ABS(I34) < 1, 1, 0) -> 1

Sheet Scenarios
A1: Scenarios & Sensitivity
A2: Change the scenario selector in cell B5 to flex the entire model. Active multipliers in section 3 are referenced by formulas in Assumptions and P&L. The tornado in section 5 is a linear approximation — for exact figures, toggle the selector and read the live model.
A4: 1. SCENARIO SELECTOR
A5: Active scenario (1=Base, 2=Downside, 3=Upside, 4=RegDelay, 5=Best, 6=Worst) | B5: 1
A6: Active scenario name | B6: =CHOOSE($B$5, "Base", "Downside", "Upside", "Reg Delay", "Best", "Worst") -> Base
A8: 2. SCENARIO DEFINITION TABLE (multipliers vs base + reg delay years)
A9: Driver | B9: Base | C9: Downside | D9: Upside | E9: Reg Delay | F9: Best | G9: Worst | M9: Interpretation
A10: Adoption ramp multiplier | B10: 1 | C10: 0.5 | D10: 1.3 | E10: 1 | F10: 1.2 | G10: 0.8 | M10: ch.13 Best/Worst: ±20% adoption around base
A11: BOM unit cost multiplier | B11: 1 | C11: 1.3 | D11: 0.85 | E11: 1 | F11: 0.9 | G11: 1.25 | M11: ch.13 Worst: cost-down slips, +20-30% (use 25%); Best: -10%
A12: Subscription churn multiplier | B12: 1 | C12: 1.5 | D12: 0.7 | E12: 1 | F12: 0.8 | G12: 1.5 | M12: ch.13: Best 8% (×0.8), Worst 15% (×1.5) from 10% base
A13: Headcount / payroll multiplier | B13: 1 | C13: 1.1 | D13: 0.95 | E13: 1.05 | F13: 1 | G13: 1.1 | M13: ch.13 Worst: burn +10% via payroll lever (dominant cost)
A14: Marketing spend multiplier | B14: 1 | C14: 1.2 | D14: 0.8 | E14: 1 | F14: 1 | G14: 1 | M14: ch.13 Best/Worst hold marketing flat; effect routed via payroll
A15: Regulatory & clinical multiplier | B15: 1 | C15: 1.5 | D15: 0.8 | E15: 1.4 | F15: 1 | G15: 1.2 | M15: Worst: extra NB / clinical cost from delay (+20%)
A16: Regulatory delay (years shifted) | B16: 0 | C16: 0 | D16: 0 | E16: 1 | F16: 0 | G16: 1 | M16: ch.13 Worst: 12-month MDR slip
A17: Hardware ASP multiplier | B17: 1 | C17: 1 | D17: 1 | E17: 1 | F17: 1.1 | G17: 0.875 | M17: ch.13: Best +10%, Worst -12.5% (mid of -10/-15%)
A18: Subscription ARPU multiplier | B18: 1 | C18: 1 | D18: 1 | E18: 1 | F18: 1.1 | G18: 0.875 | M18: ch.13: Best +10%, Worst -12.5% (mid of -10/-15%)
A19: 3. ACTIVE MULTIPLIERS (live values used by Assumptions and P&L)
A20: Adoption multiplier (active) | B20: =CHOOSE($B$5, $B$10, $C$10, $D$10, $E$10, $F$10, $G$10) -> 1
A21: BOM unit cost multiplier (active) | B21: =CHOOSE($B$5, $B$11, $C$11, $D$11, $E$11, $F$11, $G$11) -> 1
A22: Subscription churn multiplier (active) | B22: =CHOOSE($B$5, $B$12, $C$12, $D$12, $E$12, $F$12, $G$12) -> 1
A23: Headcount / payroll multiplier (active) | B23: =CHOOSE($B$5, $B$13, $C$13, $D$13, $E$13, $F$13, $G$13) -> 1
A24: Marketing spend multiplier (active) | B24: =CHOOSE($B$5, $B$14, $C$14, $D$14, $E$14, $F$14, $G$14) -> 1
A25: Regulatory & clinical multiplier (active) | B25: =CHOOSE($B$5, $B$15, $C$15, $D$15, $E$15, $F$15, $G$15) -> 1
A26: Regulatory delay (years, active) | B26: =CHOOSE($B$5, $B$16, $C$16, $D$16, $E$16, $F$16, $G$16) -> 0
A27: Hardware ASP multiplier (active) | B27: =CHOOSE($B$5, $B$17, $C$17, $D$17, $E$17, $F$17, $G$17) -> 1
A28: Subscription ARPU multiplier (active) | B28: =CHOOSE($B$5, $B$18, $C$18, $D$18, $E$18, $F$18, $G$18) -> 1
A30: 4. ACTIVE SCENARIO HEADLINE OUTPUTS (live, recomputes when selector changes)
A31: Active scenario name | B31: =$B$6 -> Base
A32: Y7 total revenue | B32: ='P&L'!I14 -> 3978956.7
A33: Y7 gross profit | B33: ='P&L'!I23 -> 2398120.7
A34: Y7 EBITDA | B34: ='P&L'!I58 -> 149150.7
A35: Y7 net income | B35: ='P&L'!I75 -> 223530.09
A36: Y7 closing cash | B36: ='Cash flow'!I39 -> 868930.97
A37: Peak unfunded cash trough | B37: ='Cash flow'!B47 -> -3708575.6
A38: First year of positive operating cash flow | B38: ='Cash flow'!B52 -> Y7
A39: Total equity raised through Y7 | B39: ='Cash flow'!B49 -> 4200000
A41: 5. APPROXIMATE TORNADO SENSITIVITY (Y7 EBITDA delta vs base, linear approx)
A42: Driver | B42: Down delta | C42: Up delta | D42: Magnitude | M42: Approximation basis
A43: Adoption ramp ±20% | B43: =-0.2 * 'P&L'!I23 -> -479624.14 | C43: =0.2 * 'P&L'!I23 -> 479624.14 | D43: =MAX(ABS(B43), ABS(C43)) -> 479624.14 | M43: ±20% × Y7 gross profit (revenue scales linearly with adoption)
A44: Blended ARPU ±15% | B44: =-0.15 * 'P&L'!I10 * 0.85 -> -223368.1 | C44: =0.15 * 'P&L'!I10 * 0.85 -> 223368.1 | D44: =MAX(ABS(B44), ABS(C44)) -> 223368.1 | M44: ±15% × Y7 sub revenue × (1 - sub COGS rate); subscription pricing lever
A45: BOM unit cost +30%/-15% | B45: =-0.3 * 'P&L'!I17 -> -395415 | C45: =0.15 * 'P&L'!I17 -> 197707.5 | D45: =MAX(ABS(B45), ABS(C45)) -> 395415 | M45: BOM change × Y7 hardware COGS (asymmetric — costs rarely fall fast)
A46: Subscription churn 10%→15% | B46: =-0.333 * 'P&L'!I10 * 0.85 -> -495877.19 | C46: =0.333 * 'P&L'!I10 * 0.85 -> 495877.19 | D46: =MAX(ABS(B46), ABS(C46)) -> 495877.19 | M46: ≈ 33% sub rev reduction: steady-state active subs scale as 1/churn, so 10%→15% gives 1/1.5 = 67% of base
A47: Hardware ASP ±15% | B47: =-0.15 * 'P&L'!I9 -> -334057.5 | C47: =0.15 * 'P&L'!I9 -> 334057.5 | D47: =MAX(ABS(B47), ABS(C47)) -> 334057.5 | M47: ±15% × Y7 hardware revenue (price flows directly to contribution)
A48: Headcount/payroll ±10% | B48: =-0.1 * Assumptions!I69 -> -128897 | C48: =0.1 * Assumptions!I69 -> 128897 | D48: =MAX(ABS(B48), ABS(C48)) -> 128897 | M48: ±10% × Y7 total people cost
A50: Read this:
A51: The driver with the largest magnitude is the most binding sensitivity. Adoption and BOM are typically the top two for hardware-led medtech. These are linear approximations — for second-order effects (and for the reg delay structural shift), toggle the scenario selector above.
